Workbook

Sheet Input
B2: Valuation Date | C2: {{ValuationDate}}
B3: Issue Date | C3: {{IssueDate}}
B4: Principal | C4: {{Principal}} | D4: {{CurrencyUnit}}
B5: Conversion Securities | C5: Series B Preferred Membershup Units
B6: Conversion Price | C6: {{ConversionPrice}}
B7: Day Basis | C7: Actual/365
B8: Maturity Date | C8: {{MaturityDate}}
B9: Extended Maturity Date | C9: =EDATE(C8,12) -> #VALUE!
B10: Interest Rate | C10: {{InterestRate}}
B11: Prepayment | C11: May not be made without consent of Holder
B12: Conversion | C12: Prior to maturity date
B13: Probability for Extension | C13: 0.7
B15: Interest Payment Schedule (No Extension):
B16: {{FirstDatetoPay}} | C16: =C$4*$C$10*YEARFRAC(B16,$C$3,3) -> #VALUE!
B17: =EDATE(B16,12) -> #VALUE! | C17: =C$4*$C$10*YEARFRAC(B17,B16,3) -> #VALUE!
B18: =EDATE(B17,12) -> #VALUE! | C18: =C$4*$C$10*YEARFRAC(B18,B17,3) -> #VALUE!
B19: =C8 -> {{MaturityDate}} | C19: =C$4*$C$10*YEARFRAC(B19,B18,3) -> #VALUE!
B21: Interest Payment Schedule (Extension):
B22: =B16 -> {{FirstDatetoPay}} | C22: =C$4*$C$10*YEARFRAC(B22,$C$3,3) -> #VALUE!
B23: =B17 -> #VALUE! | C23: =C$4*$C$10*YEARFRAC(B23,B22,3) -> #VALUE!
B24: =B18 -> #VALUE! | C24: =C$4*$C$10*YEARFRAC(B24,B23,3) -> #VALUE!
B25: =EDATE(B24,12) -> #VALUE! | C25: =C$4*$C$10*YEARFRAC(B25,B24,3) -> #VALUE!
B26: =C9 -> #VALUE! | C26: =C$4*$C$10*YEARFRAC(B26,B25,3) -> #VALUE!

Sheet Summary
B2: Summary | C2: =Input!D4 -> {{CurrencyUnit}}
B3: Valuation Date | C3: =Input!C2 -> {{ValuationDate}}
B5: Results: | C5: No Extension Scenario
B6: Liability Component | C6: =Summary!C3 -> {{ValuationDate}}
B7: Conversion Component | C7: =C8-C6 -> #VALUE!
B8: Fair Value | C8: ='Full CB'!C37 -> #VALUE!
B10: Principal Outstanding | C10: ='Full CB'!C22 -> {{Principal}}
B11: Difference | C11: =(E8-C10) -> #VALUE!

Sheet Full CB
B2: Full CB | G2: Date | H2: =C5 -> {{IssueDate}} | I2: ='Straight Debt'!B14 -> {{FirstDatetoPay}} | J2: ='Straight Debt'!B15 -> #VALUE! | K2: ='Straight Debt'!B16 -> #VALUE! | L2: ='Straight Debt'!B17 -> {{MaturityDate}}
B3: Valuation Date | C3: =Summary!C3 -> {{ValuationDate}}
G4: Steps | K4: =ROUNDDOWN(YEARFRAC(K2,$C$3,3)/$C$30,0)+1 -> #VALUE! | L4: =C29 -> 100
B5: Issue Date | C5: =Input!C3 -> {{IssueDate}} | G5: Interest Payment | K5: =Input!C18 -> #VALUE! | L5: =Input!C19 -> #VALUE!
B6: Maturity Date | C6: =Input!C8 -> {{MaturityDate}}
B7: State Date of Conversion Period | C7: =C5 -> {{IssueDate}}
B8: End Date of Conversion Period | C8: =C6 -> {{MaturityDate}}
B9: Spot Price of Series B Preferred Membership Units | C9: {{SportPrice}}
B10: Strike Price (USD) | C10: =Input!C6 -> {{ConversionPrice}}
B11: Discount Rate (Annual) | C11: ='Straight Debt'!C10 -> 0
B12: Discount Rate (Cont.) | C12: =LN(1+C11) -> 0
B13: Risk-free Rate (Annual) | C13: ='Straight Debt'!C6 -> {{RiskFreeRate}}
B14: Risk-free Rate (Cont.) | C14: =LN(1+C13) -> #VALUE!
B15: Volatility | C15: {{Volatility}}
B16: Dividend Yield | C16: {{DividendYield}}
B17: Bond Life (year) | C17: =YEARFRAC(C3,C6,3) -> #VALUE!
B18: Redemption Premium (Maturity) | C18: 1
B19: Coupon | C19: 0.1
B20: Accrued Interest (USD) | C20: =C22*C19*YEARFRAC(C21,C3,3) -> #VALUE!
B21: Last Coupon Payment Date | C21: {{LastCouponPaymentDate}} | G21: 0 | H21: =IF( (COLUMN()-COLUMN($G$21)) <= $C$29, (COLUMN()-COLUMN($G$21)), "" ) -> 1 | I21: =IF( (COLUMN()-COLUMN($G$21)) <= $C$29, (COLUMN()-COLUMN($G$21)), "" ) -> 2 | J21: =IF( (COLUMN()-COLUMN($G$21)) <= $C$29, (COLUMN()-COLUMN($G$21)), "" ) -> 3 | K21: =IF( (COLUMN()-COLUMN($G$21)) <= $C$29, (COLUMN()-COLUMN($G$21)), "" ) -> 4 | L21: =IF( (COLUMN()-COLUMN($G$21)) <= $C$29, (COLUMN()-COLUMN($G$21)), "" ) -> 5 | M21: =IF( (COLUMN()-COLUMN($G$21)) <= $C$29, (COLUMN()-COLUMN($G$21)), "" ) -> 6 | N21: =IF( (COLUMN()-COLUMN($G$21)) <= $C$29, (COLUMN()-COLUMN($G$21)), "" ) -> 7 | O21: =IF( (COLUMN()-COLUMN($G$21)) <= $C$29, (COLUMN()-COLUMN($G$21)), "" ) -> 8 | ... XFD21: =IF( (COLUMN()-COLUMN($G$21)) <= $C$29, (COLUMN()-COLUMN($G$21)), "" )
B22: Outstanding Principal of CB (USD) | C22: =Input!C4 -> {{Principal}} | E22: Date | G22: =$C$3 -> {{ValuationDate}} | H22: =$G$22+($C$6-$C$3)/$C$29*G21 -> #VALUE! | I22: =$G$22+($C$6-$C$3)/$C$29*I21 -> #VALUE! | J22: =$G$22+($C$6-$C$3)/$C$29*J21 -> #VALUE! | K22: =$G$22+($C$6-$C$3)/$C$29*K21 -> #VALUE! | L22: =$G$22+($C$6-$C$3)/$C$29*L21 -> #VALUE! | M22: =$G$22+($C$6-$C$3)/$C$29*M21 -> #VALUE! | N22: =$G$22+($C$6-$C$3)/$C$29*N21 -> #VALUE! | O22: =$G$22+($C$6-$C$3)/$C$29*O21 -> #VALUE! | P22: =$G$22+($C$6-$C$3)/$C$29*P21 -> #VALUE! | ... DC22: =$G$22+($C$6-$C$3)/$C$29*DC21 -> #VALUE!
B23: No. of Options | C23: =C22/C10 -> #VALUE! | E23: No. of Years | G23: =YEARFRAC($G$22,G22,0) -> #VALUE! | H23: =YEARFRAC($G$22,H22,0) -> #VALUE! | I23: =YEARFRAC($G$22,I22,0) -> #VALUE! | J23: =YEARFRAC($G$22,J22,0) -> #VALUE! | K23: =YEARFRAC($G$22,K22,0) -> #VALUE! | L23: =YEARFRAC($G$22,L22,0) -> #VALUE! | M23: =YEARFRAC($G$22,M22,0) -> #VALUE! | N23: =YEARFRAC($G$22,N22,0) -> #VALUE! | ... DC23: =YEARFRAC($G$22,DC22,0) -> #VALUE!
B24: Oustanding Number of Shares | C24: {{OustandingNumberofShares}}
B25: Total Principal Outstanding (USD) | C25: =C22 -> {{Principal}} | E25: Stock Price Binomial Tree | G25: =C9 -> {{SportPrice}} | H25: =G25*$C$32 -> #VALUE! | I25: =H25*$C$32 -> #VALUE! | J25: =I25*$C$32 -> #VALUE! | K25: =J25*$C$32 -> #VALUE! | L25: =K25*$C$32 -> #VALUE! | M25: =L25*$C$32 -> #VALUE! | N25: =M25*$C$32 -> #VALUE! | O25: =N25*$C$32 -> #VALUE! | ... DC25: =DB25*$C$32 -> #VALUE!
B26: Total No. of Shares to be Issued | C26: =C25/C10 -> #VALUE! | H26: =G25*$C$33 -> #VALUE! | I26: =G25*$C$32*$C$33 -> #VALUE! | J26: =H25*$C$32*$C$33 -> #VALUE! | K26: =I25*$C$32*$C$33 -> #VALUE! | L26: =J25*$C$32*$C$33 -> #VALUE! | M26: =K25*$C$32*$C$33 -> #VALUE! | N26: =L25*$C$32*$C$33 -> #VALUE! | O26: =M25*$C$32*$C$33 -> #VALUE! | P26: =N25*$C$32*$C$33 -> #VALUE! | ... DC26: =DA25*$C$32*$C$33 -> #VALUE!
B27: Dilution Effect | C27: {{DilutionEffect}} | I27: =H26*$C$33 -> #VALUE! | J27: =H26*$C$32*$C$33 -> #VALUE! | K27: =I26*$C$32*$C$33 -> #VALUE! | L27: =J26*$C$32*$C$33 -> #VALUE! | M27: =K26*$C$32*$C$33 -> #VALUE! | N27: =L26*$C$32*$C$33 -> #VALUE! | O27: =M26*$C$32*$C$33 -> #VALUE! | P27: =N26*$C$32*$C$33 -> #VALUE! | Q27: =O26*$C$32*$C$33 -> #VALUE! | ... DC27: =DA26*$C$32*$C$33 -> #VALUE!
J28: =I27*$C$33 -> #VALUE! | K28: =I27*$C$32*$C$33 -> #VALUE! | L28: =J27*$C$32*$C$33 -> #VALUE! | M28: =K27*$C$32*$C$33 -> #VALUE! | N28: =L27*$C$32*$C$33 -> #VALUE! | O28: =M27*$C$32*$C$33 -> #VALUE! | P28: =N27*$C$32*$C$33 -> #VALUE! | Q28: =O27*$C$32*$C$33 -> #VALUE! | R28: =P27*$C$32*$C$33 -> #VALUE! | ... DC28: =DA27*$C$32*$C$33 -> #VALUE!
B29: Steps | C29: 100 | K29: =J28*$C$33 -> #VALUE! | L29: =J28*$C$32*$C$33 -> #VALUE! | M29: =K28*$C$32*$C$33 -> #VALUE! | N29: =L28*$C$32*$C$33 -> #VALUE! | O29: =M28*$C$32*$C$33 -> #VALUE! | P29: =N28*$C$32*$C$33 -> #VALUE! | Q29: =O28*$C$32*$C$33 -> #VALUE! | R29: =P28*$C$32*$C$33 -> #VALUE! | S29: =Q28*$C$32*$C$33 -> #VALUE! | ... DC29: =DA28*$C$32*$C$33 -> #VALUE!
B30: Delta | C30: =C17/C29 -> #VALUE! | L30: =K29*$C$33 -> #VALUE! | M30: =K29*$C$32*$C$33 -> #VALUE! | N30: =L29*$C$32*$C$33 -> #VALUE! | O30: =M29*$C$32*$C$33 -> #VALUE! | P30: =N29*$C$32*$C$33 -> #VALUE! | Q30: =O29*$C$32*$C$33 -> #VALUE! | R30: =P29*$C$32*$C$33 -> #VALUE! | S30: =Q29*$C$32*$C$33 -> #VALUE! | T30: =R29*$C$32*$C$33 -> #VALUE! | ... DC30: =DA29*$C$32*$C$33 -> #VALUE!
M31: =L30*$C$33 -> #VALUE! | N31: =L30*$C$32*$C$33 -> #VALUE! | O31: =M30*$C$32*$C$33 -> #VALUE! | P31: =N30*$C$32*$C$33 -> #VALUE! | Q31: =O30*$C$32*$C$33 -> #VALUE! | R31: =P30*$C$32*$C$33 -> #VALUE! | S31: =Q30*$C$32*$C$33 -> #VALUE! | T31: =R30*$C$32*$C$33 -> #VALUE! | U31: =S30*$C$32*$C$33 -> #VALUE! | ... DC31: =DA30*$C$32*$C$33 -> #VALUE!
B32: U | C32: =EXP(C15*SQRT(C30)) -> #VALUE! | N32: =M31*$C$33 -> #VALUE! | O32: =M31*$C$32*$C$33 -> #VALUE! | P32: =N31*$C$32*$C$33 -> #VALUE! | Q32: =O31*$C$32*$C$33 -> #VALUE! | R32: =P31*$C$32*$C$33 -> #VALUE! | S32: =Q31*$C$32*$C$33 -> #VALUE! | T32: =R31*$C$32*$C$33 -> #VALUE! | U32: =S31*$C$32*$C$33 -> #VALUE! | V32: =T31*$C$32*$C$33 -> #VALUE! | ... DC32: =DA31*$C$32*$C$33 -> #VALUE!
B33: D | C33: =1/C32 -> #VALUE! | O33: =N32*$C$33 -> #VALUE! | P33: =N32*$C$32*$C$33 -> #VALUE! | Q33: =O32*$C$32*$C$33 -> #VALUE! | R33: =P32*$C$32*$C$33 -> #VALUE! | S33: =Q32*$C$32*$C$33 -> #VALUE! | T33: =R32*$C$32*$C$33 -> #VALUE! | U33: =S32*$C$32*$C$33 -> #VALUE! | V33: =T32*$C$32*$C$33 -> #VALUE! | W33: =U32*$C$32*$C$33 -> #VALUE! | ... DC33: =DA32*$C$32*$C$33 -> #VALUE!
B34: P | C34: =(EXP((C14-C16)*C30)-C33)/(C32-C33) -> #VALUE! | P34: =O33*$C$33 -> #VALUE! | Q34: =O33*$C$32*$C$33 -> #VALUE! | R34: =P33*$C$32*$C$33 -> #VALUE! | S34: =Q33*$C$32*$C$33 -> #VALUE! | T34: =R33*$C$32*$C$33 -> #VALUE! | U34: =S33*$C$32*$C$33 -> #VALUE! | V34: =T33*$C$32*$C$33 -> #VALUE! | W34: =U33*$C$32*$C$33 -> #VALUE! | X34: =V33*$C$32*$C$33 -> #VALUE! | ... DC34: =DA33*$C$32*$C$33 -> #VALUE!
B35: 1-P | C35: =1-C34 -> #VALUE! | Q35: =P34*$C$33 -> #VALUE! | R35: =P34*$C$32*$C$33 -> #VALUE! | S35: =Q34*$C$32*$C$33 -> #VALUE! | T35: =R34*$C$32*$C$33 -> #VALUE! | U35: =S34*$C$32*$C$33 -> #VALUE! | V35: =T34*$C$32*$C$33 -> #VALUE! | W35: =U34*$C$32*$C$33 -> #VALUE! | X35: =V34*$C$32*$C$33 -> #VALUE! | Y35: =W34*$C$32*$C$33 -> #VALUE! | ... DC35: =DA34*$C$32*$C$33 -> #VALUE!
R36: =Q35*$C$33 -> #VALUE! | S36: =Q35*$C$32*$C$33 -> #VALUE! | T36: =R35*$C$32*$C$33 -> #VALUE! | U36: =S35*$C$32*$C$33 -> #VALUE! | V36: =T35*$C$32*$C$33 -> #VALUE! | W36: =U35*$C$32*$C$33 -> #VALUE! | X36: =V35*$C$32*$C$33 -> #VALUE! | Y36: =W35*$C$32*$C$33 -> #VALUE! | Z36: =X35*$C$32*$C$33 -> #VALUE! | ... DC36: =DA35*$C$32*$C$33 -> #VALUE!
B37: Total CB Value (HK$) | C37: =ROUND(G238+G345,-4) -> #VALUE! | S37: =R36*$C$33 -> #VALUE! | T37: =R36*$C$32*$C$33 -> #VALUE! | U37: =S36*$C$32*$C$33 -> #VALUE! | V37: =T36*$C$32*$C$33 -> #VALUE! | W37: =U36*$C$32*$C$33 -> #VALUE! | X37: =V36*$C$32*$C$33 -> #VALUE! | Y37: =W36*$C$32*$C$33 -> #VALUE! | Z37: =X36*$C$32*$C$33 -> #VALUE! | AA37: =Y36*$C$32*$C$33 -> #VALUE! | ... DC37: =DA36*$C$32*$C$33 -> #VALUE!
T38: =S37*$C$33 -> #VALUE! | U38: =S37*$C$32*$C$33 -> #VALUE! | V38: =T37*$C$32*$C$33 -> #VALUE! | W38: =U37*$C$32*$C$33 -> #VALUE! | X38: =V37*$C$32*$C$33 -> #VALUE! | Y38: =W37*$C$32*$C$33 -> #VALUE! | Z38: =X37*$C$32*$C$33 -> #VALUE! | AA38: =Y37*$C$32*$C$33 -> #VALUE! | AB38: =Z37*$C$32*$C$33 -> #VALUE! | ... DC38: =DA37*$C$32*$C$33 -> #VALUE!
C39: =C37-C22 -> #VALUE! | U39: =T38*$C$33 -> #VALUE! | V39: =T38*$C$32*$C$33 -> #VALUE! | W39: =U38*$C$32*$C$33 -> #VALUE! | X39: =V38*$C$32*$C$33 -> #VALUE! | Y39: =W38*$C$32*$C$33 -> #VALUE! | Z39: =X38*$C$32*$C$33 -> #VALUE! | AA39: =Y38*$C$32*$C$33 -> #VALUE! | AB39: =Z38*$C$32*$C$33 -> #VALUE! | AC39: =AA38*$C$32*$C$33 -> #VALUE! | ... DC39: =DA38*$C$32*$C$33 -> #VALUE!
V40: =U39*$C$33 -> #VALUE! | W40: =U39*$C$32*$C$33 -> #VALUE! | X40: =V39*$C$32*$C$33 -> #VALUE! | Y40: =W39*$C$32*$C$33 -> #VALUE! | Z40: =X39*$C$32*$C$33 -> #VALUE! | AA40: =Y39*$C$32*$C$33 -> #VALUE! | AB40: =Z39*$C$32*$C$33 -> #VALUE! | AC40: =AA39*$C$32*$C$33 -> #VALUE! | AD40: =AB39*$C$32*$C$33 -> #VALUE! | ... DC40: =DA39*$C$32*$C$33 -> #VALUE!
W41: =V40*$C$33 -> #VALUE! | X41: =V40*$C$32*$C$33 -> #VALUE! | Y41: =W40*$C$32*$C$33 -> #VALUE! | Z41: =X40*$C$32*$C$33 -> #VALUE! | AA41: =Y40*$C$32*$C$33 -> #VALUE! | AB41: =Z40*$C$32*$C$33 -> #VALUE! | AC41: =AA40*$C$32*$C$33 -> #VALUE! | AD41: =AB40*$C$32*$C$33 -> #VALUE! | AE41: =AC40*$C$32*$C$33 -> #VALUE! | ... DC41: =DA40*$C$32*$C$33 -> #VALUE!
X42: =W41*$C$33 -> #VALUE! | Y42: =W41*$C$32*$C$33 -> #VALUE! | Z42: =X41*$C$32*$C$33 -> #VALUE! | AA42: =Y41*$C$32*$C$33 -> #VALUE! | AB42: =Z41*$C$32*$C$33 -> #VALUE! | AC42: =AA41*$C$32*$C$33 -> #VALUE! | AD42: =AB41*$C$32*$C$33 -> #VALUE! | AE42: =AC41*$C$32*$C$33 -> #VALUE! | AF42: =AD41*$C$32*$C$33 -> #VALUE! | ... DC42: =DA41*$C$32*$C$33 -> #VALUE!
Y43: =X42*$C$33 -> #VALUE! | Z43: =X42*$C$32*$C$33 -> #VALUE! | AA43: =Y42*$C$32*$C$33 -> #VALUE! | AB43: =Z42*$C$32*$C$33 -> #VALUE! | AC43: =AA42*$C$32*$C$33 -> #VALUE! | AD43: =AB42*$C$32*$C$33 -> #VALUE! | AE43: =AC42*$C$32*$C$33 -> #VALUE! | AF43: =AD42*$C$32*$C$33 -> #VALUE! | AG43: =AE42*$C$32*$C$33 -> #VALUE! | ... DC43: =DA42*$C$32*$C$33 -> #VALUE!
Z44: =Y43*$C$33 -> #VALUE! | AA44: =Y43*$C$32*$C$33 -> #VALUE! | AB44: =Z43*$C$32*$C$33 -> #VALUE! | AC44: =AA43*$C$32*$C$33 -> #VALUE! | AD44: =AB43*$C$32*$C$33 -> #VALUE! | AE44: =AC43*$C$32*$C$33 -> #VALUE! | AF44: =AD43*$C$32*$C$33 -> #VALUE! | AG44: =AE43*$C$32*$C$33 -> #VALUE! | AH44: =AF43*$C$32*$C$33 -> #VALUE! | ... DC44: =DA43*$C$32*$C$33 -> #VALUE!
AA45: =Z44*$C$33 -> #VALUE! | AB45: =Z44*$C$32*$C$33 -> #VALUE! | AC45: =AA44*$C$32*$C$33 -> #VALUE! | AD45: =AB44*$C$32*$C$33 -> #VALUE! | AE45: =AC44*$C$32*$C$33 -> #VALUE! | AF45: =AD44*$C$32*$C$33 -> #VALUE! | AG45: =AE44*$C$32*$C$33 -> #VALUE! | AH45: =AF44*$C$32*$C$33 -> #VALUE! | AI45: =AG44*$C$32*$C$33 -> #VALUE! | ... DC45: =DA44*$C$32*$C$33 -> #VALUE!
AB46: =AA45*$C$33 -> #VALUE! | AC46: =AA45*$C$32*$C$33 -> #VALUE! | AD46: =AB45*$C$32*$C$33 -> #VALUE! | AE46: =AC45*$C$32*$C$33 -> #VALUE! | AF46: =AD45*$C$32*$C$33 -> #VALUE! | AG46: =AE45*$C$32*$C$33 -> #VALUE! | AH46: =AF45*$C$32*$C$33 -> #VALUE! | AI46: =AG45*$C$32*$C$33 -> #VALUE! | AJ46: =AH45*$C$32*$C$33 -> #VALUE! | ... DC46: =DA45*$C$32*$C$33 -> #VALUE!
AC47: =AB46*$C$33 -> #VALUE! | AD47: =AB46*$C$32*$C$33 -> #VALUE! | AE47: =AC46*$C$32*$C$33 -> #VALUE! | AF47: =AD46*$C$32*$C$33 -> #VALUE! | AG47: =AE46*$C$32*$C$33 -> #VALUE! | AH47: =AF46*$C$32*$C$33 -> #VALUE! | AI47: =AG46*$C$32*$C$33 -> #VALUE! | AJ47: =AH46*$C$32*$C$33 -> #VALUE! | AK47: =AI46*$C$32*$C$33 -> #VALUE! | ... DC47: =DA46*$C$32*$C$33 -> #VALUE!
AD48: =AC47*$C$33 -> #VALUE! | AE48: =AC47*$C$32*$C$33 -> #VALUE! | AF48: =AD47*$C$32*$C$33 -> #VALUE! | AG48: =AE47*$C$32*$C$33 -> #VALUE! | AH48: =AF47*$C$32*$C$33 -> #VALUE! | AI48: =AG47*$C$32*$C$33 -> #VALUE! | AJ48: =AH47*$C$32*$C$33 -> #VALUE! | AK48: =AI47*$C$32*$C$33 -> #VALUE! | AL48: =AJ47*$C$32*$C$33 -> #VALUE! | ... DC48: =DA47*$C$32*$C$33 -> #VALUE!
AE49: =AD48*$C$33 -> #VALUE! | AF49: =AD48*$C$32*$C$33 -> #VALUE! | AG49: =AE48*$C$32*$C$33 -> #VALUE! | AH49: =AF48*$C$32*$C$33 -> #VALUE! | AI49: =AG48*$C$32*$C$33 -> #VALUE! | AJ49: =AH48*$C$32*$C$33 -> #VALUE! | AK49: =AI48*$C$32*$C$33 -> #VALUE! | AL49: =AJ48*$C$32*$C$33 -> #VALUE! | AM49: =AK48*$C$32*$C$33 -> #VALUE! | ... DC49: =DA48*$C$32*$C$33 -> #VALUE!
AF50: =AE49*$C$33 -> #VALUE! | AG50: =AE49*$C$32*$C$33 -> #VALUE! | AH50: =AF49*$C$32*$C$33 -> #VALUE! | AI50: =AG49*$C$32*$C$33 -> #VALUE! | AJ50: =AH49*$C$32*$C$33 -> #VALUE! | AK50: =AI49*$C$32*$C$33 -> #VALUE! | AL50: =AJ49*$C$32*$C$33 -> #VALUE! | AM50: =AK49*$C$32*$C$33 -> #VALUE! | AN50: =AL49*$C$32*$C$33 -> #VALUE! | ... DC50: =DA49*$C$32*$C$33 -> #VALUE!
AG51: =AF50*$C$33 -> #VALUE! | AH51: =AF50*$C$32*$C$33 -> #VALUE! | AI51: =AG50*$C$32*$C$33 -> #VALUE! | AJ51: =AH50*$C$32*$C$33 -> #VALUE! | AK51: =AI50*$C$32*$C$33 -> #VALUE! | AL51: =AJ50*$C$32*$C$33 -> #VALUE! | AM51: =AK50*$C$32*$C$33 -> #VALUE! | AN51: =AL50*$C$32*$C$33 -> #VALUE! | AO51: =AM50*$C$32*$C$33 -> #VALUE! | ... DC51: =DA50*$C$32*$C$33 -> #VALUE!
AH52: =AG51*$C$33 -> #VALUE! | AI52: =AG51*$C$32*$C$33 -> #VALUE! | AJ52: =AH51*$C$32*$C$33 -> #VALUE! | AK52: =AI51*$C$32*$C$33 -> #VALUE! | AL52: =AJ51*$C$32*$C$33 -> #VALUE! | AM52: =AK51*$C$32*$C$33 -> #VALUE! | AN52: =AL51*$C$32*$C$33 -> #VALUE! | AO52: =AM51*$C$32*$C$33 -> #VALUE! | AP52: =AN51*$C$32*$C$33 -> #VALUE! | ... DC52: =DA51*$C$32*$C$33 -> #VALUE!
AI53: =AH52*$C$33 -> #VALUE! | AJ53: =AH52*$C$32*$C$33 -> #VALUE! | AK53: =AI52*$C$32*$C$33 -> #VALUE! | AL53: =AJ52*$C$32*$C$33 -> #VALUE! | AM53: =AK52*$C$32*$C$33 -> #VALUE! | AN53: =AL52*$C$32*$C$33 -> #VALUE! | AO53: =AM52*$C$32*$C$33 -> #VALUE! | AP53: =AN52*$C$32*$C$33 -> #VALUE! | AQ53: =AO52*$C$32*$C$33 -> #VALUE! | ... DC53: =DA52*$C$32*$C$33 -> #VALUE!
AJ54: =AI53*$C$33 -> #VALUE! | AK54: =AI53*$C$32*$C$33 -> #VALUE! | AL54: =AJ53*$C$32*$C$33 -> #VALUE! | AM54: =AK53*$C$32*$C$33 -> #VALUE! | AN54: =AL53*$C$32*$C$33 -> #VALUE! | AO54: =AM53*$C$32*$C$33 -> #VALUE! | AP54: =AN53*$C$32*$C$33 -> #VALUE! | AQ54: =AO53*$C$32*$C$33 -> #VALUE! | AR54: =AP53*$C$32*$C$33 -> #VALUE! | ... DC54: =DA53*$C$32*$C$33 -> #VALUE!
AK55: =AJ54*$C$33 -> #VALUE! | AL55: =AJ54*$C$32*$C$33 -> #VALUE! | AM55: =AK54*$C$32*$C$33 -> #VALUE! | AN55: =AL54*$C$32*$C$33 -> #VALUE! | AO55: =AM54*$C$32*$C$33 -> #VALUE! | AP55: =AN54*$C$32*$C$33 -> #VALUE! | AQ55: =AO54*$C$32*$C$33 -> #VALUE! | AR55: =AP54*$C$32*$C$33 -> #VALUE! | AS55: =AQ54*$C$32*$C$33 -> #VALUE! | ... DC55: =DA54*$C$32*$C$33 -> #VALUE!
AL56: =AK55*$C$33 -> #VALUE! | AM56: =AK55*$C$32*$C$33 -> #VALUE! | AN56: =AL55*$C$32*$C$33 -> #VALUE! | AO56: =AM55*$C$32*$C$33 -> #VALUE! | AP56: =AN55*$C$32*$C$33 -> #VALUE! | AQ56: =AO55*$C$32*$C$33 -> #VALUE! | AR56: =AP55*$C$32*$C$33 -> #VALUE! | AS56: =AQ55*$C$32*$C$33 -> #VALUE! | AT56: =AR55*$C$32*$C$33 -> #VALUE! | ... DC56: =DA55*$C$32*$C$33 -> #VALUE!
AM57: =AL56*$C$33 -> #VALUE! | AN57: =AL56*$C$32*$C$33 -> #VALUE! | AO57: =AM56*$C$32*$C$33 -> #VALUE! | AP57: =AN56*$C$32*$C$33 -> #VALUE! | AQ57: =AO56*$C$32*$C$33 -> #VALUE! | AR57: =AP56*$C$32*$C$33 -> #VALUE! | AS57: =AQ56*$C$32*$C$33 -> #VALUE! | AT57: =AR56*$C$32*$C$33 -> #VALUE! | AU57: =AS56*$C$32*$C$33 -> #VALUE! | ... DC57: =DA56*$C$32*$C$33 -> #VALUE!
AN58: =AM57*$C$33 -> #VALUE! | AO58: =AM57*$C$32*$C$33 -> #VALUE! | AP58: =AN57*$C$32*$C$33 -> #VALUE! | AQ58: =AO57*$C$32*$C$33 -> #VALUE! | AR58: =AP57*$C$32*$C$33 -> #VALUE! | AS58: =AQ57*$C$32*$C$33 -> #VALUE! | AT58: =AR57*$C$32*$C$33 -> #VALUE! | AU58: =AS57*$C$32*$C$33 -> #VALUE! | AV58: =AT57*$C$32*$C$33 -> #VALUE! | ... DC58: =DA57*$C$32*$C$33 -> #VALUE!
AO59: =AN58*$C$33 -> #VALUE! | AP59: =AN58*$C$32*$C$33 -> #VALUE! | AQ59: =AO58*$C$32*$C$33 -> #VALUE! | AR59: =AP58*$C$32*$C$33 -> #VALUE! | AS59: =AQ58*$C$32*$C$33 -> #VALUE! | AT59: =AR58*$C$32*$C$33 -> #VALUE! | AU59: =AS58*$C$32*$C$33 -> #VALUE! | AV59: =AT58*$C$32*$C$33 -> #VALUE! | AW59: =AU58*$C$32*$C$33 -> #VALUE! | ... DC59: =DA58*$C$32*$C$33 -> #VALUE!
AP60: =AO59*$C$33 -> #VALUE! | AQ60: =AO59*$C$32*$C$33 -> #VALUE! | AR60: =AP59*$C$32*$C$33 -> #VALUE! | AS60: =AQ59*$C$32*$C$33 -> #VALUE! | AT60: =AR59*$C$32*$C$33 -> #VALUE! | AU60: =AS59*$C$32*$C$33 -> #VALUE! | AV60: =AT59*$C$32*$C$33 -> #VALUE! | AW60: =AU59*$C$32*$C$33 -> #VALUE! | AX60: =AV59*$C$32*$C$33 -> #VALUE! | ... DC60: =DA59*$C$32*$C$33 -> #VALUE!
AQ61: =AP60*$C$33 -> #VALUE! | AR61: =AP60*$C$32*$C$33 -> #VALUE! | AS61: =AQ60*$C$32*$C$33 -> #VALUE! | AT61: =AR60*$C$32*$C$33 -> #VALUE! | AU61: =AS60*$C$32*$C$33 -> #VALUE! | AV61: =AT60*$C$32*$C$33 -> #VALUE! | AW61: =AU60*$C$32*$C$33 -> #VALUE! | AX61: =AV60*$C$32*$C$33 -> #VALUE! | AY61: =AW60*$C$32*$C$33 -> #VALUE! | ... DC61: =DA60*$C$32*$C$33 -> #VALUE!
AR62: =AQ61*$C$33 -> #VALUE! | AS62: =AQ61*$C$32*$C$33 -> #VALUE! | AT62: =AR61*$C$32*$C$33 -> #VALUE! | AU62: =AS61*$C$32*$C$33 -> #VALUE! | AV62: =AT61*$C$32*$C$33 -> #VALUE! | AW62: =AU61*$C$32*$C$33 -> #VALUE! | AX62: =AV61*$C$32*$C$33 -> #VALUE! | AY62: =AW61*$C$32*$C$33 -> #VALUE! | AZ62: =AX61*$C$32*$C$33 -> #VALUE! | ... DC62: =DA61*$C$32*$C$33 -> #VALUE!
AS63: =AR62*$C$33 -> #VALUE! | AT63: =AR62*$C$32*$C$33 -> #VALUE! | AU63: =AS62*$C$32*$C$33 -> #VALUE! | AV63: =AT62*$C$32*$C$33 -> #VALUE! | AW63: =AU62*$C$32*$C$33 -> #VALUE! | AX63: =AV62*$C$32*$C$33 -> #VALUE! | AY63: =AW62*$C$32*$C$33 -> #VALUE! | AZ63: =AX62*$C$32*$C$33 -> #VALUE! | BA63: =AY62*$C$32*$C$33 -> #VALUE! | ... DC63: =DA62*$C$32*$C$33 -> #VALUE!
AT64: =AS63*$C$33 -> #VALUE! | AU64: =AS63*$C$32*$C$33 -> #VALUE! | AV64: =AT63*$C$32*$C$33 -> #VALUE! | AW64: =AU63*$C$32*$C$33 -> #VALUE! | AX64: =AV63*$C$32*$C$33 -> #VALUE! | AY64: =AW63*$C$32*$C$33 -> #VALUE! | AZ64: =AX63*$C$32*$C$33 -> #VALUE! | BA64: =AY63*$C$32*$C$33 -> #VALUE! | BB64: =AZ63*$C$32*$C$33 -> #VALUE! | ... DC64: =DA63*$C$32*$C$33 -> #VALUE!
AU65: =AT64*$C$33 -> #VALUE! | AV65: =AT64*$C$32*$C$33 -> #VALUE! | AW65: =AU64*$C$32*$C$33 -> #VALUE! | AX65: =AV64*$C$32*$C$33 -> #VALUE! | AY65: =AW64*$C$32*$C$33 -> #VALUE! | AZ65: =AX64*$C$32*$C$33 -> #VALUE! | BA65: =AY64*$C$32*$C$33 -> #VALUE! | BB65: =AZ64*$C$32*$C$33 -> #VALUE! | BC65: =BA64*$C$32*$C$33 -> #VALUE! | ... DC65: =DA64*$C$32*$C$33 -> #VALUE!
AV66: =AU65*$C$33 -> #VALUE! | AW66: =AU65*$C$32*$C$33 -> #VALUE! | AX66: =AV65*$C$32*$C$33 -> #VALUE! | AY66: =AW65*$C$32*$C$33 -> #VALUE! | AZ66: =AX65*$C$32*$C$33 -> #VALUE! | BA66: =AY65*$C$32*$C$33 -> #VALUE! | BB66: =AZ65*$C$32*$C$33 -> #VALUE! | BC66: =BA65*$C$32*$C$33 -> #VALUE! | BD66: =BB65*$C$32*$C$33 -> #VALUE! | ... DC66: =DA65*$C$32*$C$33 -> #VALUE!
AW67: =AV66*$C$33 -> #VALUE! | AX67: =AV66*$C$32*$C$33 -> #VALUE! | AY67: =AW66*$C$32*$C$33 -> #VALUE! | AZ67: =AX66*$C$32*$C$33 -> #VALUE! | BA67: =AY66*$C$32*$C$33 -> #VALUE! | BB67: =AZ66*$C$32*$C$33 -> #VALUE! | BC67: =BA66*$C$32*$C$33 -> #VALUE! | BD67: =BB66*$C$32*$C$33 -> #VALUE! | BE67: =BC66*$C$32*$C$33 -> #VALUE! | ... DC67: =DA66*$C$32*$C$33 -> #VALUE!
AX68: =AW67*$C$33 -> #VALUE! | AY68: =AW67*$C$32*$C$33 -> #VALUE! | AZ68: =AX67*$C$32*$C$33 -> #VALUE! | BA68: =AY67*$C$32*$C$33 -> #VALUE! | BB68: =AZ67*$C$32*$C$33 -> #VALUE! | BC68: =BA67*$C$32*$C$33 -> #VALUE! | BD68: =BB67*$C$32*$C$33 -> #VALUE! | BE68: =BC67*$C$32*$C$33 -> #VALUE! | BF68: =BD67*$C$32*$C$33 -> #VALUE! | ... DC68: =DA67*$C$32*$C$33 -> #VALUE!
AY69: =AX68*$C$33 -> #VALUE! | AZ69: =AX68*$C$32*$C$33 -> #VALUE! | BA69: =AY68*$C$32*$C$33 -> #VALUE! | BB69: =AZ68*$C$32*$C$33 -> #VALUE! | BC69: =BA68*$C$32*$C$33 -> #VALUE! | BD69: =BB68*$C$32*$C$33 -> #VALUE! | BE69: =BC68*$C$32*$C$33 -> #VALUE! | BF69: =BD68*$C$32*$C$33 -> #VALUE! | BG69: =BE68*$C$32*$C$33 -> #VALUE! | ... DC69: =DA68*$C$32*$C$33 -> #VALUE!
AZ70: =AY69*$C$33 -> #VALUE! | BA70: =AY69*$C$32*$C$33 -> #VALUE! | BB70: =AZ69*$C$32*$C$33 -> #VALUE! | BC70: =BA69*$C$32*$C$33 -> #VALUE! | BD70: =BB69*$C$32*$C$33 -> #VALUE! | BE70: =BC69*$C$32*$C$33 -> #VALUE! | BF70: =BD69*$C$32*$C$33 -> #VALUE! | BG70: =BE69*$C$32*$C$33 -> #VALUE! | BH70: =BF69*$C$32*$C$33 -> #VALUE! | ... DC70: =DA69*$C$32*$C$33 -> #VALUE!
BA71: =AZ70*$C$33 -> #VALUE! | BB71: =AZ70*$C$32*$C$33 -> #VALUE! | BC71: =BA70*$C$32*$C$33 -> #VALUE! | BD71: =BB70*$C$32*$C$33 -> #VALUE! | BE71: =BC70*$C$32*$C$33 -> #VALUE! | BF71: =BD70*$C$32*$C$33 -> #VALUE! | BG71: =BE70*$C$32*$C$33 -> #VALUE! | BH71: =BF70*$C$32*$C$33 -> #VALUE! | BI71: =BG70*$C$32*$C$33 -> #VALUE! | ... DC71: =DA70*$C$32*$C$33 -> #VALUE!
BB72: =BA71*$C$33 -> #VALUE! | BC72: =BA71*$C$32*$C$33 -> #VALUE! | BD72: =BB71*$C$32*$C$33 -> #VALUE! | BE72: =BC71*$C$32*$C$33 -> #VALUE! | BF72: =BD71*$C$32*$C$33 -> #VALUE! | BG72: =BE71*$C$32*$C$33 -> #VALUE! | BH72: =BF71*$C$32*$C$33 -> #VALUE! | BI72: =BG71*$C$32*$C$33 -> #VALUE! | BJ72: =BH71*$C$32*$C$33 -> #VALUE! | ... DC72: =DA71*$C$32*$C$33 -> #VALUE!
BC73: =BB72*$C$33 -> #VALUE! | BD73: =BB72*$C$32*$C$33 -> #VALUE! | BE73: =BC72*$C$32*$C$33 -> #VALUE! | BF73: =BD72*$C$32*$C$33 -> #VALUE! | BG73: =BE72*$C$32*$C$33 -> #VALUE! | BH73: =BF72*$C$32*$C$33 -> #VALUE! | BI73: =BG72*$C$32*$C$33 -> #VALUE! | BJ73: =BH72*$C$32*$C$33 -> #VALUE! | BK73: =BI72*$C$32*$C$33 -> #VALUE! | ... DC73: =DA72*$C$32*$C$33 -> #VALUE!
BD74: =BC73*$C$33 -> #VALUE! | BE74: =BC73*$C$32*$C$33 -> #VALUE! | BF74: =BD73*$C$32*$C$33 -> #VALUE! | BG74: =BE73*$C$32*$C$33 -> #VALUE! | BH74: =BF73*$C$32*$C$33 -> #VALUE! | BI74: =BG73*$C$32*$C$33 -> #VALUE! | BJ74: =BH73*$C$32*$C$33 -> #VALUE! | BK74: =BI73*$C$32*$C$33 -> #VALUE! | BL74: =BJ73*$C$32*$C$33 -> #VALUE! | ... DC74: =DA73*$C$32*$C$33 -> #VALUE!
BE75: =BD74*$C$33 -> #VALUE! | BF75: =BD74*$C$32*$C$33 -> #VALUE! | BG75: =BE74*$C$32*$C$33 -> #VALUE! | BH75: =BF74*$C$32*$C$33 -> #VALUE! | BI75: =BG74*$C$32*$C$33 -> #VALUE! | BJ75: =BH74*$C$32*$C$33 -> #VALUE! | BK75: =BI74*$C$32*$C$33 -> #VALUE! | BL75: =BJ74*$C$32*$C$33 -> #VALUE! | BM75: =BK74*$C$32*$C$33 -> #VALUE! | ... DC75: =DA74*$C$32*$C$33 -> #VALUE!
BF76: =BE75*$C$33 -> #VALUE! | BG76: =BE75*$C$32*$C$33 -> #VALUE! | BH76: =BF75*$C$32*$C$33 -> #VALUE! | BI76: =BG75*$C$32*$C$33 -> #VALUE! | BJ76: =BH75*$C$32*$C$33 -> #VALUE! | BK76: =BI75*$C$32*$C$33 -> #VALUE! | BL76: =BJ75*$C$32*$C$33 -> #VALUE! | BM76: =BK75*$C$32*$C$33 -> #VALUE! | BN76: =BL75*$C$32*$C$33 -> #VALUE! | ... DC76: =DA75*$C$32*$C$33 -> #VALUE!
BG77: =BF76*$C$33 -> #VALUE! | BH77: =BF76*$C$32*$C$33 -> #VALUE! | BI77: =BG76*$C$32*$C$33 -> #VALUE! | BJ77: =BH76*$C$32*$C$33 -> #VALUE! | BK77: =BI76*$C$32*$C$33 -> #VALUE! | BL77: =BJ76*$C$32*$C$33 -> #VALUE! | BM77: =BK76*$C$32*$C$33 -> #VALUE! | BN77: =BL76*$C$32*$C$33 -> #VALUE! | BO77: =BM76*$C$32*$C$33 -> #VALUE! | ... DC77: =DA76*$C$32*$C$33 -> #VALUE!
BH78: =BG77*$C$33 -> #VALUE! | BI78: =BG77*$C$32*$C$33 -> #VALUE! | BJ78: =BH77*$C$32*$C$33 -> #VALUE! | BK78: =BI77*$C$32*$C$33 -> #VALUE! | BL78: =BJ77*$C$32*$C$33 -> #VALUE! | BM78: =BK77*$C$32*$C$33 -> #VALUE! | BN78: =BL77*$C$32*$C$33 -> #VALUE! | BO78: =BM77*$C$32*$C$33 -> #VALUE! | BP78: =BN77*$C$32*$C$33 -> #VALUE! | ... DC78: =DA77*$C$32*$C$33 -> #VALUE!
BI79: =BH78*$C$33 -> #VALUE! | BJ79: =BH78*$C$32*$C$33 -> #VALUE! | BK79: =BI78*$C$32*$C$33 -> #VALUE! | BL79: =BJ78*$C$32*$C$33 -> #VALUE! | BM79: =BK78*$C$32*$C$33 -> #VALUE! | BN79: =BL78*$C$32*$C$33 -> #VALUE! | BO79: =BM78*$C$32*$C$33 -> #VALUE! | BP79: =BN78*$C$32*$C$33 -> #VALUE! | BQ79: =BO78*$C$32*$C$33 -> #VALUE! | ... DC79: =DA78*$C$32*$C$33 -> #VALUE!
BJ80: =BI79*$C$33 -> #VALUE! | BK80: =BI79*$C$32*$C$33 -> #VALUE! | BL80: =BJ79*$C$32*$C$33 -> #VALUE! | BM80: =BK79*$C$32*$C$33 -> #VALUE! | BN80: =BL79*$C$32*$C$33 -> #VALUE! | BO80: =BM79*$C$32*$C$33 -> #VALUE! | BP80: =BN79*$C$32*$C$33 -> #VALUE! | BQ80: =BO79*$C$32*$C$33 -> #VALUE! | BR80: =BP79*$C$32*$C$33 -> #VALUE! | ... DC80: =DA79*$C$32*$C$33 -> #VALUE!
BK81: =BJ80*$C$33 -> #VALUE! | BL81: =BJ80*$C$32*$C$33 -> #VALUE! | BM81: =BK80*$C$32*$C$33 -> #VALUE! | BN81: =BL80*$C$32*$C$33 -> #VALUE! | BO81: =BM80*$C$32*$C$33 -> #VALUE! | BP81: =BN80*$C$32*$C$33 -> #VALUE! | BQ81: =BO80*$C$32*$C$33 -> #VALUE! | BR81: =BP80*$C$32*$C$33 -> #VALUE! | BS81: =BQ80*$C$32*$C$33 -> #VALUE! | ... DC81: =DA80*$C$32*$C$33 -> #VALUE!
BL82: =BK81*$C$33 -> #VALUE! | BM82: =BK81*$C$32*$C$33 -> #VALUE! | BN82: =BL81*$C$32*$C$33 -> #VALUE! | BO82: =BM81*$C$32*$C$33 -> #VALUE! | BP82: =BN81*$C$32*$C$33 -> #VALUE! | BQ82: =BO81*$C$32*$C$33 -> #VALUE! | BR82: =BP81*$C$32*$C$33 -> #VALUE! | BS82: =BQ81*$C$32*$C$33 -> #VALUE! | BT82: =BR81*$C$32*$C$33 -> #VALUE! | ... DC82: =DA81*$C$32*$C$33 -> #VALUE!
BM83: =BL82*$C$33 -> #VALUE! | BN83: =BL82*$C$32*$C$33 -> #VALUE! | BO83: =BM82*$C$32*$C$33 -> #VALUE! | BP83: =BN82*$C$32*$C$33 -> #VALUE! | BQ83: =BO82*$C$32*$C$33 -> #VALUE! | BR83: =BP82*$C$32*$C$33 -> #VALUE! | BS83: =BQ82*$C$32*$C$33 -> #VALUE! | BT83: =BR82*$C$32*$C$33 -> #VALUE! | BU83: =BS82*$C$32*$C$33 -> #VALUE! | ... DC83: =DA82*$C$32*$C$33 -> #VALUE!
BN84: =BM83*$C$33 -> #VALUE! | BO84: =BM83*$C$32*$C$33 -> #VALUE! | BP84: =BN83*$C$32*$C$33 -> #VALUE! | BQ84: =BO83*$C$32*$C$33 -> #VALUE! | BR84: =BP83*$C$32*$C$33 -> #VALUE! | BS84: =BQ83*$C$32*$C$33 -> #VALUE! | BT84: =BR83*$C$32*$C$33 -> #VALUE! | BU84: =BS83*$C$32*$C$33 -> #VALUE! | BV84: =BT83*$C$32*$C$33 -> #VALUE! | ... DC84: =DA83*$C$32*$C$33 -> #VALUE!
BO85: =BN84*$C$33 -> #VALUE! | BP85: =BN84*$C$32*$C$33 -> #VALUE! | BQ85: =BO84*$C$32*$C$33 -> #VALUE! | BR85: =BP84*$C$32*$C$33 -> #VALUE! | BS85: =BQ84*$C$32*$C$33 -> #VALUE! | BT85: =BR84*$C$32*$C$33 -> #VALUE! | BU85: =BS84*$C$32*$C$33 -> #VALUE! | BV85: =BT84*$C$32*$C$33 -> #VALUE! | BW85: =BU84*$C$32*$C$33 -> #VALUE! | ... DC85: =DA84*$C$32*$C$33 -> #VALUE!
BP86: =BO85*$C$33 -> #VALUE! | BQ86: =BO85*$C$32*$C$33 -> #VALUE! | BR86: =BP85*$C$32*$C$33 -> #VALUE! | BS86: =BQ85*$C$32*$C$33 -> #VALUE! | BT86: =BR85*$C$32*$C$33 -> #VALUE! | BU86: =BS85*$C$32*$C$33 -> #VALUE! | BV86: =BT85*$C$32*$C$33 -> #VALUE! | BW86: =BU85*$C$32*$C$33 -> #VALUE! | BX86: =BV85*$C$32*$C$33 -> #VALUE! | ... DC86: =DA85*$C$32*$C$33 -> #VALUE!
BQ87: =BP86*$C$33 -> #VALUE! | BR87: =BP86*$C$32*$C$33 -> #VALUE! | BS87: =BQ86*$C$32*$C$33 -> #VALUE! | BT87: =BR86*$C$32*$C$33 -> #VALUE! | BU87: =BS86*$C$32*$C$33 -> #VALUE! | BV87: =BT86*$C$32*$C$33 -> #VALUE! | BW87: =BU86*$C$32*$C$33 -> #VALUE! | BX87: =BV86*$C$32*$C$33 -> #VALUE! | BY87: =BW86*$C$32*$C$33 -> #VALUE! | ... DC87: =DA86*$C$32*$C$33 -> #VALUE!
BR88: =BQ87*$C$33 -> #VALUE! | BS88: =BQ87*$C$32*$C$33 -> #VALUE! | BT88: =BR87*$C$32*$C$33 -> #VALUE! | BU88: =BS87*$C$32*$C$33 -> #VALUE! | BV88: =BT87*$C$32*$C$33 -> #VALUE! | BW88: =BU87*$C$32*$C$33 -> #VALUE! | BX88: =BV87*$C$32*$C$33 -> #VALUE! | BY88: =BW87*$C$32*$C$33 -> #VALUE! | BZ88: =BX87*$C$32*$C$33 -> #VALUE! | ... DC88: =DA87*$C$32*$C$33 -> #VALUE!
BS89: =BR88*$C$33 -> #VALUE! | BT89: =BR88*$C$32*$C$33 -> #VALUE! | BU89: =BS88*$C$32*$C$33 -> #VALUE! | BV89: =BT88*$C$32*$C$33 -> #VALUE! | BW89: =BU88*$C$32*$C$33 -> #VALUE! | BX89: =BV88*$C$32*$C$33 -> #VALUE! | BY89: =BW88*$C$32*$C$33 -> #VALUE! | BZ89: =BX88*$C$32*$C$33 -> #VALUE! | CA89: =BY88*$C$32*$C$33 -> #VALUE! | ... DC89: =DA88*$C$32*$C$33 -> #VALUE!
BT90: =BS89*$C$33 -> #VALUE! | BU90: =BS89*$C$32*$C$33 -> #VALUE! | BV90: =BT89*$C$32*$C$33 -> #VALUE! | BW90: =BU89*$C$32*$C$33 -> #VALUE! | BX90: =BV89*$C$32*$C$33 -> #VALUE! | BY90: =BW89*$C$32*$C$33 -> #VALUE! | BZ90: =BX89*$C$32*$C$33 -> #VALUE! | CA90: =BY89*$C$32*$C$33 -> #VALUE! | CB90: =BZ89*$C$32*$C$33 -> #VALUE! | ... DC90: =DA89*$C$32*$C$33 -> #VALUE!
BU91: =BT90*$C$33 -> #VALUE! | BV91: =BT90*$C$32*$C$33 -> #VALUE! | BW91: =BU90*$C$32*$C$33 -> #VALUE! | BX91: =BV90*$C$32*$C$33 -> #VALUE! | BY91: =BW90*$C$32*$C$33 -> #VALUE! | BZ91: =BX90*$C$32*$C$33 -> #VALUE! | CA91: =BY90*$C$32*$C$33 -> #VALUE! | CB91: =BZ90*$C$32*$C$33 -> #VALUE! | CC91: =CA90*$C$32*$C$33 -> #VALUE! | ... DC91: =DA90*$C$32*$C$33 -> #VALUE!
BV92: =BU91*$C$33 -> #VALUE! | BW92: =BU91*$C$32*$C$33 -> #VALUE! | BX92: =BV91*$C$32*$C$33 -> #VALUE! | BY92: =BW91*$C$32*$C$33 -> #VALUE! | BZ92: =BX91*$C$32*$C$33 -> #VALUE! | CA92: =BY91*$C$32*$C$33 -> #VALUE! | CB92: =BZ91*$C$32*$C$33 -> #VALUE! | CC92: =CA91*$C$32*$C$33 -> #VALUE! | CD92: =CB91*$C$32*$C$33 -> #VALUE! | ... DC92: =DA91*$C$32*$C$33 -> #VALUE!
BW93: =BV92*$C$33 -> #VALUE! | BX93: =BV92*$C$32*$C$33 -> #VALUE! | BY93: =BW92*$C$32*$C$33 -> #VALUE! | BZ93: =BX92*$C$32*$C$33 -> #VALUE! | CA93: =BY92*$C$32*$C$33 -> #VALUE! | CB93: =BZ92*$C$32*$C$33 -> #VALUE! | CC93: =CA92*$C$32*$C$33 -> #VALUE! | CD93: =CB92*$C$32*$C$33 -> #VALUE! | CE93: =CC92*$C$32*$C$33 -> #VALUE! | ... DC93: =DA92*$C$32*$C$33 -> #VALUE!
BX94: =BW93*$C$33 -> #VALUE! | BY94: =BW93*$C$32*$C$33 -> #VALUE! | BZ94: =BX93*$C$32*$C$33 -> #VALUE! | CA94: =BY93*$C$32*$C$33 -> #VALUE! | CB94: =BZ93*$C$32*$C$33 -> #VALUE! | CC94: =CA93*$C$32*$C$33 -> #VALUE! | CD94: =CB93*$C$32*$C$33 -> #VALUE! | CE94: =CC93*$C$32*$C$33 -> #VALUE! | CF94: =CD93*$C$32*$C$33 -> #VALUE! | ... DC94: =DA93*$C$32*$C$33 -> #VALUE!
BY95: =BX94*$C$33 -> #VALUE! | BZ95: =BX94*$C$32*$C$33 -> #VALUE! | CA95: =BY94*$C$32*$C$33 -> #VALUE! | CB95: =BZ94*$C$32*$C$33 -> #VALUE! | CC95: =CA94*$C$32*$C$33 -> #VALUE! | CD95: =CB94*$C$32*$C$33 -> #VALUE! | CE95: =CC94*$C$32*$C$33 -> #VALUE! | CF95: =CD94*$C$32*$C$33 -> #VALUE! | CG95: =CE94*$C$32*$C$33 -> #VALUE! | ... DC95: =DA94*$C$32*$C$33 -> #VALUE!
BZ96: =BY95*$C$33 -> #VALUE! | CA96: =BY95*$C$32*$C$33 -> #VALUE! | CB96: =BZ95*$C$32*$C$33 -> #VALUE! | CC96: =CA95*$C$32*$C$33 -> #VALUE! | CD96: =CB95*$C$32*$C$33 -> #VALUE! | CE96: =CC95*$C$32*$C$33 -> #VALUE! | CF96: =CD95*$C$32*$C$33 -> #VALUE! | CG96: =CE95*$C$32*$C$33 -> #VALUE! | CH96: =CF95*$C$32*$C$33 -> #VALUE! | ... DC96: =DA95*$C$32*$C$33 -> #VALUE!
CA97: =BZ96*$C$33 -> #VALUE! | CB97: =BZ96*$C$32*$C$33 -> #VALUE! | CC97: =CA96*$C$32*$C$33 -> #VALUE! | CD97: =CB96*$C$32*$C$33 -> #VALUE! | CE97: =CC96*$C$32*$C$33 -> #VALUE! | CF97: =CD96*$C$32*$C$33 -> #VALUE! | CG97: =CE96*$C$32*$C$33 -> #VALUE! | CH97: =CF96*$C$32*$C$33 -> #VALUE! | CI97: =CG96*$C$32*$C$33 -> #VALUE! | ... DC97: =DA96*$C$32*$C$33 -> #VALUE!
CB98: =CA97*$C$33 -> #VALUE! | CC98: =CA97*$C$32*$C$33 -> #VALUE! | CD98: =CB97*$C$32*$C$33 -> #VALUE! | CE98: =CC97*$C$32*$C$33 -> #VALUE! | CF98: =CD97*$C$32*$C$33 -> #VALUE! | CG98: =CE97*$C$32*$C$33 -> #VALUE! | CH98: =CF97*$C$32*$C$33 -> #VALUE! | CI98: =CG97*$C$32*$C$33 -> #VALUE! | CJ98: =CH97*$C$32*$C$33 -> #VALUE! | ... DC98: =DA97*$C$32*$C$33 -> #VALUE!
CC99: =CB98*$C$33 -> #VALUE! | CD99: =CB98*$C$32*$C$33 -> #VALUE! | CE99: =CC98*$C$32*$C$33 -> #VALUE! | CF99: =CD98*$C$32*$C$33 -> #VALUE! | CG99: =CE98*$C$32*$C$33 -> #VALUE! | CH99: =CF98*$C$32*$C$33 -> #VALUE! | CI99: =CG98*$C$32*$C$33 -> #VALUE! | CJ99: =CH98*$C$32*$C$33 -> #VALUE! | CK99: =CI98*$C$32*$C$33 -> #VALUE! | ... DC99: =DA98*$C$32*$C$33 -> #VALUE!
CD100: =CC99*$C$33 -> #VALUE! | CE100: =CC99*$C$32*$C$33 -> #VALUE! | CF100: =CD99*$C$32*$C$33 -> #VALUE! | CG100: =CE99*$C$32*$C$33 -> #VALUE! | CH100: =CF99*$C$32*$C$33 -> #VALUE! | CI100: =CG99*$C$32*$C$33 -> #VALUE! | CJ100: =CH99*$C$32*$C$33 -> #VALUE! | CK100: =CI99*$C$32*$C$33 -> #VALUE! | CL100: =CJ99*$C$32*$C$33 -> #VALUE! | ... DC100: =DA99*$C$32*$C$33 -> #VALUE!
CE101: =CD100*$C$33 -> #VALUE! | CF101: =CD100*$C$32*$C$33 -> #VALUE! | CG101: =CE100*$C$32*$C$33 -> #VALUE! | CH101: =CF100*$C$32*$C$33 -> #VALUE! | CI101: =CG100*$C$32*$C$33 -> #VALUE! | CJ101: =CH100*$C$32*$C$33 -> #VALUE! | CK101: =CI100*$C$32*$C$33 -> #VALUE! | CL101: =CJ100*$C$32*$C$33 -> #VALUE! | CM101: =CK100*$C$32*$C$33 -> #VALUE! | ... DC101: =DA100*$C$32*$C$33 -> #VALUE!
...

Sheet Straight Debt
B2: Straight Debt
B3: Valuation Date | C3: =Input!C2 -> {{ValuationDate}}
B5: Risky Rate:
B6: Rfr | C6: {{RiskFreeRate}}
B7: OAS | C7: {{CreditRiskPremium}}
B8: Liquidity | C8: {{LiquidityRiskPremium}}
B9: Other Risk | C9: {{OtherRisk}}
B10: Total | C10: =SUM(C6:C9) -> 0
B13: Date | C13: Interest Payment | D13: Principal Repayment | E13: TTM | F13: PV
B14: =Input!B16 -> {{FirstDatetoPay}}
B15: =Input!B17 -> #VALUE!
B16: =Input!B18 -> #VALUE! | C16: =Input!C18 -> #VALUE! | E16: =YEARFRAC(B16,$C$3,3) -> #VALUE! | F16: =SUM(C16:D16)/(1+$C$10)^E16 -> #VALUE!
B17: =Input!B19 -> {{MaturityDate}} | C17: =Input!C19 -> #VALUE! | D17: =Input!C4 -> {{Principal}} | E17: =YEARFRAC(B17,$C$3,3) -> #VALUE! | F17: =SUM(C17:D17)/(1+$C$10)^E17 -> #VALUE!
B18: Total PV | F18: =ROUND(SUM(F14:F17),-4) -> #VALUE!
D20: ß
