Workbook

Sheet Summary
B2: Summary | C2: USD
B3: Valuation Date | C3: =Input!C2 -> 45838
B5: Results: | C5: No Extension Scenario | D5: Exension Scenario | E5: Prob% Weighted Average
B6: Liability Component | C6: ='Straight Debt'!F18 -> 7780000 | D6: ='Straight Debt_Extend'!F19 -> 6050000 | E6: =C6*(1-Input!$C$13)+D6*Input!$C$13 -> 6569000
B7: Conversion Component | C7: =C8-C6 -> 0 | D7: =D8-D6 -> 10000 | E7: =C7*(1-Input!$C$13)+D7*Input!$C$13 -> 7000
B8: Fair Value | C8: ='Full CB'!C37 -> 7780000 | D8: ='Full CB_Extend'!C37 -> 6060000 | E8: =SUM(E6:E7) -> 6576000 | F8: <-- FV of the CB
B10: Principal Outstanding | C10: ='Full CB'!C22 -> 10000000
B11: Difference | C11: =(E8-C10) -> -3424000

Sheet Full CB
B2: Full CB | G2: Date | H2: =C5 -> 45121 | I2: {=TRANSPOSE(Input!B16:B19)} -> 45291 | J2: 45657 | K2: 46022 | L2: 46217
B3: Valuation Date | C3: =Input!C2 -> 45838
G4: Steps | I4: =MIN( IF(I2<C3, -1, ROUNDDOWN(YEARFRAC(I2, $C$3, 3)/$C$30, 0)+1), 100 ) -> -1 | J4: =MIN( IF(J2<C3, -1, ROUNDDOWN(YEARFRAC(J2, $C$3, 3)/$C$30, 0)+1), 100 ) -> -1 | K4: =MIN( IF(K2<C3, -1, ROUNDDOWN(YEARFRAC(K2, $C$3, 3)/$C$30, 0)+1), 100 ) -> 49 | L4: =MIN( IF(L2<C3, -1, ROUNDDOWN(YEARFRAC(L2, $C$3, 3)/$C$30, 0)+1), 100 ) -> 100 | M4: =MIN( IF(M2<C3, -1, ROUNDDOWN(YEARFRAC(M2, $C$3, 3)/$C$30, 0)+1), 100 ) -> -1 | N4: =MIN( IF(N2<C3, -1, ROUNDDOWN(YEARFRAC(N2, $C$3, 3)/$C$30, 0)+1), 100 ) -> -1 | O4: =MIN( IF(O2<C3, -1, ROUNDDOWN(YEARFRAC(O2, $C$3, 3)/$C$30, 0)+1), 100 ) -> -1
B5: Issue Date | C5: =Input!C3 -> 45121 | D5: =C5 -> 45121 | G5: Interest Payment | K5: =Input!C18 -> 1000000 | L5: =Input!C19 -> 534246.58
B6: Maturity Date | C6: =Input!C8 -> 46217 | D6: =C6 -> 46217
B7: State Date of Conversion Period | C7: =C5 -> 45121 | D7: =C7 -> 45121
B8: End Date of Conversion Period | C8: =C6 -> 46217 | D8: =C8 -> 46217
B9: Spot Price of Series B Preferred Membership Units | C9: 1226574 | D9: Based on allocation as at 2025/6/30
B10: Strike Price (USD) | C10: =Input!C6 -> 5484545.2
B11: Discount Rate (Annual) | C11: ='Risky Rate'!C7 -> 0.49075828
B12: Discount Rate (Cont.) | C12: =LN(1+C11) -> 0.39928491
B13: Risk-free Rate (Annual) | C13: ='Risky Rate'!C3 -> 0.039623726
B14: Risk-free Rate (Cont.) | C14: =LN(1+C13) -> 0.038858846
B15: Volatility | C15: =Vol!G14 -> 0.37833444
B16: Dividend Yield | C16: 0
B17: Bond Life (year) | C17: =YEARFRAC(C3,C6,3) -> 1.0383562
B18: Redemption Premium (Maturity) | C18: 1
B19: Coupon | C19: 0.1
B20: Accrued Interest (USD) | C20: =C22*C19*YEARFRAC(C21,C3,3) -> 495890.41
B21: Last Coupon Payment Date | C21: =DATE(2024,12,31) -> 45657 | G21: 0 | H21: 1 | I21: 2 | J21: 3 | K21: 4 | L21: 5 | M21: 6 | N21: 7 | O21: 8 | P21: 9 | Q21: 10 | R21: 11 | S21: 12 | T21: 13 | U21: 14 | V21: 15 | W21: 16 | X21: 17 | Y21: 18 | Z21: 19 | AA21: 20 | AB21: 21 | AC21: 22 | AD21: 23 | AE21: 24 | AF21: 25 | AG21: 26 | AH21: 27 | AI21: 28 | AJ21: 29 | AK21: 30 | AL21: 31 | AM21: 32 | AN21: 33 | AO21: 34 | AP21: 35 | AQ21: 36 | AR21: 37 | AS21: 38 | AT21: 39 | AU21: 40 | AV21: 41 | AW21: 42 | AX21: 43 | AY21: 44 | AZ21: 45 | BA21: 46 | BB21: 47 | BC21: 48 | BD21: 49 | BE21: 50 | BF21: 51 | BG21: 52 | BH21: 53 | BI21: 54 | BJ21: 55 | BK21: 56 | BL21: 57 | BM21: 58 | BN21: 59 | BO21: 60 | BP21: 61 | BQ21: 62 | BR21: 63 | BS21: 64 | BT21: 65 | BU21: 66 | BV21: 67 | BW21: 68 | BX21: 69 | BY21: 70 | BZ21: 71 | CA21: 72 | CB21: 73 | CC21: 74 | CD21: 75 | CE21: 76 | CF21: 77 | CG21: 78 | CH21: 79 | CI21: 80 | CJ21: 81 | CK21: 82 | CL21: 83 | CM21: 84 | CN21: 85 | CO21: 86 | CP21: 87 | CQ21: 88 | CR21: 89 | CS21: 90 | CT21: 91 | CU21: 92 | CV21: 93 | CW21: 94 | CX21: 95 | CY21: 96 | CZ21: 97 | DA21: 98 | DB21: 99 | DC21: 100
B22: Outstanding Principal of CB (USD) | C22: =Input!C4 -> 10000000 | E22: Date | G22: =$C$3 -> 45838 | H22: =$G$22+($C$6-$C$3)/$C$29*H21 -> 45841.79 | I22: =$G$22+($C$6-$C$3)/$C$29*I21 -> 45845.58 | J22: =$G$22+($C$6-$C$3)/$C$29*J21 -> 45849.37 | K22: =$G$22+($C$6-$C$3)/$C$29*K21 -> 45853.16 | L22: =$G$22+($C$6-$C$3)/$C$29*L21 -> 45856.95 | M22: =$G$22+($C$6-$C$3)/$C$29*M21 -> 45860.74 | N22: =$G$22+($C$6-$C$3)/$C$29*N21 -> 45864.53 | O22: =$G$22+($C$6-$C$3)/$C$29*O21 -> 45868.32 | ... DC22: =$G$22+($C$6-$C$3)/$C$29*DC21 -> 46217
B23: No. of Options | C23: =C22/C10 -> 1.8233052 | E23: No. of Years | G23: =YEARFRAC($G$22,G22,0) -> 0 | H23: =YEARFRAC($G$22,H22,0) -> 0.0083333333 | I23: =YEARFRAC($G$22,I22,0) -> 0.019444444 | J23: =YEARFRAC($G$22,J22,0) -> 0.030555556 | K23: =YEARFRAC($G$22,K22,0) -> 0.041666667 | L23: =YEARFRAC($G$22,L22,0) -> 0.05 | M23: =YEARFRAC($G$22,M22,0) -> 0.061111111 | N23: =YEARFRAC($G$22,N22,0) -> 0.072222222 | ... DC23: =YEARFRAC($G$22,DC22,0) -> 1.0388889
B24: Oustanding Number of Shares | C24: 68.773706
B25: Total Principal Outstanding (USD) | C25: =C22 -> 10000000 | E25: Stock Price Binomial Tree | G25: =C9 -> 1226574 | H25: =G25*$C$32 -> 1274784.5 | I25: =H25*$C$32 -> 1324889.9 | J25: =I25*$C$32 -> 1376964.6 | K25: =J25*$C$32 -> 1431086.2 | L25: =K25*$C$32 -> 1487335 | M25: =L25*$C$32 -> 1545794.6 | N25: =M25*$C$32 -> 1606552 | O25: =N25*$C$32 -> 1669697.5 | ... DC25: =DB25*$C$32 -> 57942084
B26: Total No. of Shares to be Issued | C26: =C25/C10 -> 1.8233052 | H26: =G25*$C$33 -> 1180186.8 | I26: =G25*$C$32*$C$33 -> 1226574 | J26: =H25*$C$32*$C$33 -> 1274784.5 | K26: =I25*$C$32*$C$33 -> 1324889.9 | L26: =J25*$C$32*$C$33 -> 1376964.6 | M26: =K25*$C$32*$C$33 -> 1431086.2 | N26: =L25*$C$32*$C$33 -> 1487335 | O26: =M25*$C$32*$C$33 -> 1545794.6 | P26: =N25*$C$32*$C$33 -> 1606552 | ... DC26: =DA25*$C$32*$C$33 -> 53642388
B27: Dilution Effect | C27: 1 | I27: =H26*$C$33 -> 1135553.9 | J27: =H26*$C$32*$C$33 -> 1180186.8 | K27: =I26*$C$32*$C$33 -> 1226574 | L27: =J26*$C$32*$C$33 -> 1274784.5 | M27: =K26*$C$32*$C$33 -> 1324889.9 | N27: =L26*$C$32*$C$33 -> 1376964.6 | O27: =M26*$C$32*$C$33 -> 1431086.2 | P27: =N26*$C$32*$C$33 -> 1487335 | Q27: =O26*$C$32*$C$33 -> 1545794.6 | ... DC27: =DA26*$C$32*$C$33 -> 49661759
J28: =I27*$C$33 -> 1092609 | K28: =I27*$C$32*$C$33 -> 1135553.9 | L28: =J27*$C$32*$C$33 -> 1180186.8 | M28: =K27*$C$32*$C$33 -> 1226574 | N28: =L27*$C$32*$C$33 -> 1274784.5 | O28: =M27*$C$32*$C$33 -> 1324889.9 | P28: =N27*$C$32*$C$33 -> 1376964.6 | Q28: =O27*$C$32*$C$33 -> 1431086.2 | R28: =P27*$C$32*$C$33 -> 1487335 | ... DC28: =DA27*$C$32*$C$33 -> 45976520
B29: Steps | C29: 100 | K29: =J28*$C$33 -> 1051288.1 | L29: =J28*$C$32*$C$33 -> 1092609 | M29: =K28*$C$32*$C$33 -> 1135553.9 | N29: =L28*$C$32*$C$33 -> 1180186.8 | O29: =M28*$C$32*$C$33 -> 1226574 | P29: =N28*$C$32*$C$33 -> 1274784.5 | Q29: =O28*$C$32*$C$33 -> 1324889.9 | R29: =P28*$C$32*$C$33 -> 1376964.6 | S29: =Q28*$C$32*$C$33 -> 1431086.2 | ... DC29: =DA28*$C$32*$C$33 -> 42564750
B30: Delta | C30: =C17/C29 -> 0.010383562 | L30: =K29*$C$33 -> 1011530 | M30: =K29*$C$32*$C$33 -> 1051288.1 | N30: =L29*$C$32*$C$33 -> 1092609 | O30: =M29*$C$32*$C$33 -> 1135553.9 | P30: =N29*$C$32*$C$33 -> 1180186.8 | Q30: =O29*$C$32*$C$33 -> 1226574 | R30: =P29*$C$32*$C$33 -> 1274784.5 | S30: =Q29*$C$32*$C$33 -> 1324889.9 | T30: =R29*$C$32*$C$33 -> 1376964.6 | ... DC30: =DA29*$C$32*$C$33 -> 39406157
M31: =L30*$C$33 -> 973275.41 | N31: =L30*$C$32*$C$33 -> 1011530 | O31: =M30*$C$32*$C$33 -> 1051288.1 | P31: =N30*$C$32*$C$33 -> 1092609 | Q31: =O30*$C$32*$C$33 -> 1135553.9 | R31: =P30*$C$32*$C$33 -> 1180186.8 | S31: =Q30*$C$32*$C$33 -> 1226574 | T31: =R30*$C$32*$C$33 -> 1274784.5 | U31: =S30*$C$32*$C$33 -> 1324889.9 | ... DC31: =DA30*$C$32*$C$33 -> 36481952
B32: U | C32: =EXP(C15*SQRT(C30)) -> 1.039305 | N32: =M31*$C$33 -> 936467.58 | O32: =M31*$C$32*$C$33 -> 973275.41 | P32: =N31*$C$32*$C$33 -> 1011530 | Q32: =O31*$C$32*$C$33 -> 1051288.1 | R32: =P31*$C$32*$C$33 -> 1092609 | S32: =Q31*$C$32*$C$33 -> 1135553.9 | T32: =R31*$C$32*$C$33 -> 1180186.8 | U32: =S31*$C$32*$C$33 -> 1226574 | V32: =T31*$C$32*$C$33 -> 1274784.5 | ... DC32: =DA31*$C$32*$C$33 -> 33774744
B33: D | C33: =1/C32 -> 0.96218149 | O33: =N32*$C$33 -> 901051.77 | P33: =N32*$C$32*$C$33 -> 936467.58 | Q33: =O32*$C$32*$C$33 -> 973275.41 | R33: =P32*$C$32*$C$33 -> 1011530 | S33: =Q32*$C$32*$C$33 -> 1051288.1 | T33: =R32*$C$32*$C$33 -> 1092609 | U33: =S32*$C$32*$C$33 -> 1135553.9 | V33: =T32*$C$32*$C$33 -> 1180186.8 | W33: =U32*$C$32*$C$33 -> 1226574 | ... DC33: =DA32*$C$32*$C$33 -> 31268429
B34: P | C34: =(EXP((C14-C16)*C30)-C33)/(C32-C33) -> 0.49559598 | P34: =O33*$C$33 -> 866975.33 | Q34: =O33*$C$32*$C$33 -> 901051.77 | R34: =P33*$C$32*$C$33 -> 936467.58 | S34: =Q33*$C$32*$C$33 -> 973275.41 | T34: =R33*$C$32*$C$33 -> 1011530 | U34: =S33*$C$32*$C$33 -> 1051288.1 | V34: =T33*$C$32*$C$33 -> 1092609 | W34: =U33*$C$32*$C$33 -> 1135553.9 | X34: =V33*$C$32*$C$33 -> 1180186.8 | ... DC34: =DA33*$C$32*$C$33 -> 28948099
B35: 1-P | C35: =1-C34 -> 0.50440402 | Q35: =P34*$C$33 -> 834187.61 | R35: =P34*$C$32*$C$33 -> 866975.33 | S35: =Q34*$C$32*$C$33 -> 901051.77 | T35: =R34*$C$32*$C$33 -> 936467.58 | U35: =S34*$C$32*$C$33 -> 973275.41 | V35: =T34*$C$32*$C$33 -> 1011530 | W35: =U34*$C$32*$C$33 -> 1051288.1 | X35: =V34*$C$32*$C$33 -> 1092609 | Y35: =W34*$C$32*$C$33 -> 1135553.9 | ... DC35: =DA34*$C$32*$C$33 -> 26799954
R36: =Q35*$C$33 -> 802639.88 | S36: =Q35*$C$32*$C$33 -> 834187.61 | T36: =R35*$C$32*$C$33 -> 866975.33 | U36: =S35*$C$32*$C$33 -> 901051.77 | V36: =T35*$C$32*$C$33 -> 936467.58 | W36: =U35*$C$32*$C$33 -> 973275.41 | X36: =V35*$C$32*$C$33 -> 1011530 | Y36: =W35*$C$32*$C$33 -> 1051288.1 | Z36: =X35*$C$32*$C$33 -> 1092609 | ... DC36: =DA35*$C$32*$C$33 -> 24811215
B37: Total CB Value (HK$) | C37: =ROUND(G238+G345,-4) -> 7780000 | S37: =R36*$C$33 -> 772285.23 | T37: =R36*$C$32*$C$33 -> 802639.88 | U37: =S36*$C$32*$C$33 -> 834187.61 | V37: =T36*$C$32*$C$33 -> 866975.33 | W37: =U36*$C$32*$C$33 -> 901051.77 | X37: =V36*$C$32*$C$33 -> 936467.58 | Y37: =W36*$C$32*$C$33 -> 973275.41 | Z37: =X36*$C$32*$C$33 -> 1011530 | AA37: =Y36*$C$32*$C$33 -> 1051288.1 | ... DC37: =DA36*$C$32*$C$33 -> 22970055
T38: =S37*$C$33 -> 743078.55 | U38: =S37*$C$32*$C$33 -> 772285.23 | V38: =T37*$C$32*$C$33 -> 802639.88 | W38: =U37*$C$32*$C$33 -> 834187.61 | X38: =V37*$C$32*$C$33 -> 866975.33 | Y38: =W37*$C$32*$C$33 -> 901051.77 | Z38: =X37*$C$32*$C$33 -> 936467.58 | AA38: =Y37*$C$32*$C$33 -> 973275.41 | AB38: =Z37*$C$32*$C$33 -> 1011530 | ... DC38: =DA37*$C$32*$C$33 -> 21265521
C39: =C37-C22 -> -2220000 | U39: =T38*$C$33 -> 714976.43 | V39: =T38*$C$32*$C$33 -> 743078.55 | W39: =U38*$C$32*$C$33 -> 772285.23 | X39: =V38*$C$32*$C$33 -> 802639.88 | Y39: =W38*$C$32*$C$33 -> 834187.61 | Z39: =X38*$C$32*$C$33 -> 866975.33 | AA39: =Y38*$C$32*$C$33 -> 901051.77 | AB39: =Z38*$C$32*$C$33 -> 936467.58 | AC39: =AA38*$C$32*$C$33 -> 973275.41 | ... DC39: =DA38*$C$32*$C$33 -> 19687475
V40: =U39*$C$33 -> 687937.08 | W40: =U39*$C$32*$C$33 -> 714976.43 | X40: =V39*$C$32*$C$33 -> 743078.55 | Y40: =W39*$C$32*$C$33 -> 772285.23 | Z40: =X39*$C$32*$C$33 -> 802639.88 | AA40: =Y39*$C$32*$C$33 -> 834187.61 | AB40: =Z39*$C$32*$C$33 -> 866975.33 | AC40: =AA39*$C$32*$C$33 -> 901051.77 | AD40: =AB39*$C$32*$C$33 -> 936467.58 | ... DC40: =DA39*$C$32*$C$33 -> 18226531
W41: =V40*$C$33 -> 661920.32 | X41: =V40*$C$32*$C$33 -> 687937.08 | Y41: =W40*$C$32*$C$33 -> 714976.43 | Z41: =X40*$C$32*$C$33 -> 743078.55 | AA41: =Y40*$C$32*$C$33 -> 772285.23 | AB41: =Z40*$C$32*$C$33 -> 802639.88 | AC41: =AA40*$C$32*$C$33 -> 834187.61 | AD41: =AB40*$C$32*$C$33 -> 866975.33 | AE41: =AC40*$C$32*$C$33 -> 901051.77 | ... DC41: =DA40*$C$32*$C$33 -> 16873998
X42: =W41*$C$33 -> 636887.48 | Y42: =W41*$C$32*$C$33 -> 661920.32 | Z42: =X41*$C$32*$C$33 -> 687937.08 | AA42: =Y41*$C$32*$C$33 -> 714976.43 | AB42: =Z41*$C$32*$C$33 -> 743078.55 | AC42: =AA41*$C$32*$C$33 -> 772285.23 | AD42: =AB41*$C$32*$C$33 -> 802639.88 | AE42: =AC41*$C$32*$C$33 -> 834187.61 | AF42: =AD41*$C$32*$C$33 -> 866975.33 | ... DC42: =DA41*$C$32*$C$33 -> 15621833
Y43: =X42*$C$33 -> 612801.34 | Z43: =X42*$C$32*$C$33 -> 636887.48 | AA43: =Y42*$C$32*$C$33 -> 661920.32 | AB43: =Z42*$C$32*$C$33 -> 687937.08 | AC43: =AA42*$C$32*$C$33 -> 714976.43 | AD43: =AB42*$C$32*$C$33 -> 743078.55 | AE43: =AC42*$C$32*$C$33 -> 772285.23 | AF43: =AD42*$C$32*$C$33 -> 802639.88 | AG43: =AE42*$C$32*$C$33 -> 834187.61 | ... DC43: =DA42*$C$32*$C$33 -> 14462587
Z44: =Y43*$C$33 -> 589626.11 | AA44: =Y43*$C$32*$C$33 -> 612801.34 | AB44: =Z43*$C$32*$C$33 -> 636887.48 | AC44: =AA43*$C$32*$C$33 -> 661920.32 | AD44: =AB43*$C$32*$C$33 -> 687937.08 | AE44: =AC43*$C$32*$C$33 -> 714976.43 | AF44: =AD43*$C$32*$C$33 -> 743078.55 | AG44: =AE43*$C$32*$C$33 -> 772285.23 | AH44: =AF43*$C$32*$C$33 -> 802639.88 | ... DC44: =DA43*$C$32*$C$33 -> 13389365
AA45: =Z44*$C$33 -> 567327.32 | AB45: =Z44*$C$32*$C$33 -> 589626.11 | AC45: =AA44*$C$32*$C$33 -> 612801.34 | AD45: =AB44*$C$32*$C$33 -> 636887.48 | AE45: =AC44*$C$32*$C$33 -> 661920.32 | AF45: =AD44*$C$32*$C$33 -> 687937.08 | AG45: =AE44*$C$32*$C$33 -> 714976.43 | AH45: =AF44*$C$32*$C$33 -> 743078.55 | AI45: =AG44*$C$32*$C$33 -> 772285.23 | ... DC45: =DA44*$C$32*$C$33 -> 12395783
AB46: =AA45*$C$33 -> 545871.85 | AC46: =AA45*$C$32*$C$33 -> 567327.32 | AD46: =AB45*$C$32*$C$33 -> 589626.11 | AE46: =AC45*$C$32*$C$33 -> 612801.34 | AF46: =AD45*$C$32*$C$33 -> 636887.48 | AG46: =AE45*$C$32*$C$33 -> 661920.32 | AH46: =AF45*$C$32*$C$33 -> 687937.08 | AI46: =AG45*$C$32*$C$33 -> 714976.43 | AJ46: =AH45*$C$32*$C$33 -> 743078.55 | ... DC46: =DA45*$C$32*$C$33 -> 11475932
AC47: =AB46*$C$33 -> 525227.79 | AD47: =AB46*$C$32*$C$33 -> 545871.85 | AE47: =AC46*$C$32*$C$33 -> 567327.32 | AF47: =AD46*$C$32*$C$33 -> 589626.11 | AG47: =AE46*$C$32*$C$33 -> 612801.34 | AH47: =AF46*$C$32*$C$33 -> 636887.48 | AI47: =AG46*$C$32*$C$33 -> 661920.32 | AJ47: =AH46*$C$32*$C$33 -> 687937.08 | AK47: =AI46*$C$32*$C$33 -> 714976.43 | ... DC47: =DA46*$C$32*$C$33 -> 10624340
AD48: =AC47*$C$33 -> 505364.45 | AE48: =AC47*$C$32*$C$33 -> 525227.79 | AF48: =AD47*$C$32*$C$33 -> 545871.85 | AG48: =AE47*$C$32*$C$33 -> 567327.32 | AH48: =AF47*$C$32*$C$33 -> 589626.11 | AI48: =AG47*$C$32*$C$33 -> 612801.34 | AJ48: =AH47*$C$32*$C$33 -> 636887.48 | AK48: =AI47*$C$32*$C$33 -> 661920.32 | AL48: =AJ47*$C$32*$C$33 -> 687937.08 | ... DC48: =DA47*$C$32*$C$33 -> 9835941.9
AE49: =AD48*$C$33 -> 486252.32 | AF49: =AD48*$C$32*$C$33 -> 505364.45 | AG49: =AE48*$C$32*$C$33 -> 525227.79 | AH49: =AF48*$C$32*$C$33 -> 545871.85 | AI49: =AG48*$C$32*$C$33 -> 567327.32 | AJ49: =AH48*$C$32*$C$33 -> 589626.11 | AK49: =AI48*$C$32*$C$33 -> 612801.34 | AL49: =AJ48*$C$32*$C$33 -> 636887.48 | AM49: =AK48*$C$32*$C$33 -> 661920.32 | ... DC49: =DA48*$C$32*$C$33 -> 9106048.3
AF50: =AE49*$C$33 -> 467862.98 | AG50: =AE49*$C$32*$C$33 -> 486252.32 | AH50: =AF49*$C$32*$C$33 -> 505364.45 | AI50: =AG49*$C$32*$C$33 -> 525227.79 | AJ50: =AH49*$C$32*$C$33 -> 545871.85 | AK50: =AI49*$C$32*$C$33 -> 567327.32 | AL50: =AJ49*$C$32*$C$33 -> 589626.11 | AM50: =AK49*$C$32*$C$33 -> 612801.34 | AN50: =AL49*$C$32*$C$33 -> 636887.48 | ... DC50: =DA49*$C$32*$C$33 -> 8430317.7
AG51: =AF50*$C$33 -> 450169.1 | AH51: =AF50*$C$32*$C$33 -> 467862.98 | AI51: =AG50*$C$32*$C$33 -> 486252.32 | AJ51: =AH50*$C$32*$C$33 -> 505364.45 | AK51: =AI50*$C$32*$C$33 -> 525227.79 | AL51: =AJ50*$C$32*$C$33 -> 545871.85 | AM51: =AK50*$C$32*$C$33 -> 567327.32 | AN51: =AL50*$C$32*$C$33 -> 589626.11 | AO51: =AM50*$C$32*$C$33 -> 612801.34 | ... DC51: =DA50*$C$32*$C$33 -> 7804730.9
AH52: =AG51*$C$33 -> 433144.37 | AI52: =AG51*$C$32*$C$33 -> 450169.1 | AJ52: =AH51*$C$32*$C$33 -> 467862.98 | AK52: =AI51*$C$32*$C$33 -> 486252.32 | AL52: =AJ51*$C$32*$C$33 -> 505364.45 | AM52: =AK51*$C$32*$C$33 -> 525227.79 | AN52: =AL51*$C$32*$C$33 -> 545871.85 | AO52: =AM51*$C$32*$C$33 -> 567327.32 | AP52: =AN51*$C$32*$C$33 -> 589626.11 | ... DC52: =DA51*$C$32*$C$33 -> 7225566.9
AI53: =AH52*$C$33 -> 416763.5 | AJ53: =AH52*$C$32*$C$33 -> 433144.37 | AK53: =AI52*$C$32*$C$33 -> 450169.1 | AL53: =AJ52*$C$32*$C$33 -> 467862.98 | AM53: =AK52*$C$32*$C$33 -> 486252.32 | AN53: =AL52*$C$32*$C$33 -> 505364.45 | AO53: =AM52*$C$32*$C$33 -> 525227.79 | AP53: =AN52*$C$32*$C$33 -> 545871.85 | AQ53: =AO52*$C$32*$C$33 -> 567327.32 | ... DC53: =DA52*$C$32*$C$33 -> 6689380.8
AJ54: =AI53*$C$33 -> 401002.12 | AK54: =AI53*$C$32*$C$33 -> 416763.5 | AL54: =AJ53*$C$32*$C$33 -> 433144.37 | AM54: =AK53*$C$32*$C$33 -> 450169.1 | AN54: =AL53*$C$32*$C$33 -> 467862.98 | AO54: =AM53*$C$32*$C$33 -> 486252.32 | AP54: =AN53*$C$32*$C$33 -> 505364.45 | AQ54: =AO53*$C$32*$C$33 -> 525227.79 | AR54: =AP53*$C$32*$C$33 -> 545871.85 | ... DC54: =DA53*$C$32*$C$33 -> 6192983.4
AK55: =AJ54*$C$33 -> 385836.82 | AL55: =AJ54*$C$32*$C$33 -> 401002.12 | AM55: =AK54*$C$32*$C$33 -> 416763.5 | AN55: =AL54*$C$32*$C$33 -> 433144.37 | AO55: =AM54*$C$32*$C$33 -> 450169.1 | AP55: =AN54*$C$32*$C$33 -> 467862.98 | AQ55: =AO54*$C$32*$C$33 -> 486252.32 | AR55: =AP54*$C$32*$C$33 -> 505364.45 | AS55: =AQ54*$C$32*$C$33 -> 525227.79 | ... DC55: =DA54*$C$32*$C$33 -> 5733422
AL56: =AK55*$C$33 -> 371245.04 | AM56: =AK55*$C$32*$C$33 -> 385836.82 | AN56: =AL55*$C$32*$C$33 -> 401002.12 | AO56: =AM55*$C$32*$C$33 -> 416763.5 | AP56: =AN55*$C$32*$C$33 -> 433144.37 | AQ56: =AO55*$C$32*$C$33 -> 450169.1 | AR56: =AP55*$C$32*$C$33 -> 467862.98 | AS56: =AQ55*$C$32*$C$33 -> 486252.32 | AT56: =AR55*$C$32*$C$33 -> 505364.45 | ... DC56: =DA55*$C$32*$C$33 -> 5307963.2
AM57: =AL56*$C$33 -> 357205.11 | AN57: =AL56*$C$32*$C$33 -> 371245.04 | AO57: =AM56*$C$32*$C$33 -> 385836.82 | AP57: =AN56*$C$32*$C$33 -> 401002.12 | AQ57: =AO56*$C$32*$C$33 -> 416763.5 | AR57: =AP56*$C$32*$C$33 -> 433144.37 | AS57: =AQ56*$C$32*$C$33 -> 450169.1 | AT57: =AR56*$C$32*$C$33 -> 467862.98 | AU57: =AS56*$C$32*$C$33 -> 486252.32 | ... DC57: =DA56*$C$32*$C$33 -> 4914076.3
AN58: =AM57*$C$33 -> 343696.14 | AO58: =AM57*$C$32*$C$33 -> 357205.11 | AP58: =AN57*$C$32*$C$33 -> 371245.04 | AQ58: =AO57*$C$32*$C$33 -> 385836.82 | AR58: =AP57*$C$32*$C$33 -> 401002.12 | AS58: =AQ57*$C$32*$C$33 -> 416763.5 | AT58: =AR57*$C$32*$C$33 -> 433144.37 | AU58: =AS57*$C$32*$C$33 -> 450169.1 | AV58: =AT57*$C$32*$C$33 -> 467862.98 | ... DC58: =DA57*$C$32*$C$33 -> 4549418.5
AO59: =AN58*$C$33 -> 330698.06 | AP59: =AN58*$C$32*$C$33 -> 343696.14 | AQ59: =AO58*$C$32*$C$33 -> 357205.11 | AR59: =AP58*$C$32*$C$33 -> 371245.04 | AS59: =AQ58*$C$32*$C$33 -> 385836.82 | AT59: =AR58*$C$32*$C$33 -> 401002.12 | AU59: =AS58*$C$32*$C$33 -> 416763.5 | AV59: =AT58*$C$32*$C$33 -> 433144.37 | AW59: =AU58*$C$32*$C$33 -> 450169.1 | ... DC59: =DA58*$C$32*$C$33 -> 4211820.8
AP60: =AO59*$C$33 -> 318191.56 | AQ60: =AO59*$C$32*$C$33 -> 330698.06 | AR60: =AP59*$C$32*$C$33 -> 343696.14 | AS60: =AQ59*$C$32*$C$33 -> 357205.11 | AT60: =AR59*$C$32*$C$33 -> 371245.04 | AU60: =AS59*$C$32*$C$33 -> 385836.82 | AV60: =AT59*$C$32*$C$33 -> 401002.12 | AW60: =AU59*$C$32*$C$33 -> 416763.5 | AX60: =AV59*$C$32*$C$33 -> 433144.37 | ... DC60: =DA59*$C$32*$C$33 -> 3899275.1
AQ61: =AP60*$C$33 -> 306158.02 | AR61: =AP60*$C$32*$C$33 -> 318191.56 | AS61: =AQ60*$C$32*$C$33 -> 330698.06 | AT61: =AR60*$C$32*$C$33 -> 343696.14 | AU61: =AS60*$C$32*$C$33 -> 357205.11 | AV61: =AT60*$C$32*$C$33 -> 371245.04 | AW61: =AU60*$C$32*$C$33 -> 385836.82 | AX61: =AV60*$C$32*$C$33 -> 401002.12 | AY61: =AW60*$C$32*$C$33 -> 416763.5 | ... DC61: =DA60*$C$32*$C$33 -> 3609922.4
AR62: =AQ61*$C$33 -> 294579.58 | AS62: =AQ61*$C$32*$C$33 -> 306158.02 | AT62: =AR61*$C$32*$C$33 -> 318191.56 | AU62: =AS61*$C$32*$C$33 -> 330698.06 | AV62: =AT61*$C$32*$C$33 -> 343696.14 | AW62: =AU61*$C$32*$C$33 -> 357205.11 | AX62: =AV61*$C$32*$C$33 -> 371245.04 | AY62: =AW61*$C$32*$C$33 -> 385836.82 | AZ62: =AX61*$C$32*$C$33 -> 401002.12 | ... DC62: =DA61*$C$32*$C$33 -> 3342041.7
AS63: =AR62*$C$33 -> 283439.02 | AT63: =AR62*$C$32*$C$33 -> 294579.58 | AU63: =AS62*$C$32*$C$33 -> 306158.02 | AV63: =AT62*$C$32*$C$33 -> 318191.56 | AW63: =AU62*$C$32*$C$33 -> 330698.06 | AX63: =AV62*$C$32*$C$33 -> 343696.14 | AY63: =AW62*$C$32*$C$33 -> 357205.11 | AZ63: =AX62*$C$32*$C$33 -> 371245.04 | BA63: =AY62*$C$32*$C$33 -> 385836.82 | ... DC63: =DA62*$C$32*$C$33 -> 3094039.5
AT64: =AS63*$C$33 -> 272719.78 | AU64: =AS63*$C$32*$C$33 -> 283439.02 | AV64: =AT63*$C$32*$C$33 -> 294579.58 | AW64: =AU63*$C$32*$C$33 -> 306158.02 | AX64: =AV63*$C$32*$C$33 -> 318191.56 | AY64: =AW63*$C$32*$C$33 -> 330698.06 | AZ64: =AX63*$C$32*$C$33 -> 343696.14 | BA64: =AY63*$C$32*$C$33 -> 357205.11 | BB64: =AZ63*$C$32*$C$33 -> 371245.04 | ... DC64: =DA63*$C$32*$C$33 -> 2864440.8
AU65: =AT64*$C$33 -> 262405.92 | AV65: =AT64*$C$32*$C$33 -> 272719.78 | AW65: =AU64*$C$32*$C$33 -> 283439.02 | AX65: =AV64*$C$32*$C$33 -> 294579.58 | AY65: =AW64*$C$32*$C$33 -> 306158.02 | AZ65: =AX64*$C$32*$C$33 -> 318191.56 | BA65: =AY64*$C$32*$C$33 -> 330698.06 | BB65: =AZ64*$C$32*$C$33 -> 343696.14 | BC65: =BA64*$C$32*$C$33 -> 357205.11 | ... DC65: =DA64*$C$32*$C$33 -> 2651879.8
AV66: =AU65*$C$33 -> 252482.12 | AW66: =AU65*$C$32*$C$33 -> 262405.92 | AX66: =AV65*$C$32*$C$33 -> 272719.78 | AY66: =AW65*$C$32*$C$33 -> 283439.02 | AZ66: =AX65*$C$32*$C$33 -> 294579.58 | BA66: =AY65*$C$32*$C$33 -> 306158.02 | BB66: =AZ65*$C$32*$C$33 -> 318191.56 | BC66: =BA65*$C$32*$C$33 -> 330698.06 | BD66: =BB65*$C$32*$C$33 -> 343696.14 | ... DC66: =DA65*$C$32*$C$33 -> 2455092.3
AW67: =AV66*$C$33 -> 242933.62 | AX67: =AV66*$C$32*$C$33 -> 252482.12 | AY67: =AW66*$C$32*$C$33 -> 262405.92 | AZ67: =AX66*$C$32*$C$33 -> 272719.78 | BA67: =AY66*$C$32*$C$33 -> 283439.02 | BB67: =AZ66*$C$32*$C$33 -> 294579.58 | BC67: =BA66*$C$32*$C$33 -> 306158.02 | BD67: =BB66*$C$32*$C$33 -> 318191.56 | BE67: =BC66*$C$32*$C$33 -> 330698.06 | ... DC67: =DA66*$C$32*$C$33 -> 2272907.8
AX68: =AW67*$C$33 -> 233746.23 | AY68: =AW67*$C$32*$C$33 -> 242933.62 | AZ68: =AX67*$C$32*$C$33 -> 252482.12 | BA68: =AY67*$C$32*$C$33 -> 262405.92 | BB68: =AZ67*$C$32*$C$33 -> 272719.78 | BC68: =BA67*$C$32*$C$33 -> 283439.02 | BD68: =BB67*$C$32*$C$33 -> 294579.58 | BE68: =BC67*$C$32*$C$33 -> 306158.02 | BF68: =BD67*$C$32*$C$33 -> 318191.56 | ... DC68: =DA67*$C$32*$C$33 -> 2104242.6
AY69: =AX68*$C$33 -> 224906.3 | AZ69: =AX68*$C$32*$C$33 -> 233746.23 | BA69: =AY68*$C$32*$C$33 -> 242933.62 | BB69: =AZ68*$C$32*$C$33 -> 252482.12 | BC69: =BA68*$C$32*$C$33 -> 262405.92 | BD69: =BB68*$C$32*$C$33 -> 272719.78 | BE69: =BC68*$C$32*$C$33 -> 283439.02 | BF69: =BD68*$C$32*$C$33 -> 294579.58 | BG69: =BE68*$C$32*$C$33 -> 306158.02 | ... DC69: =DA68*$C$32*$C$33 -> 1948093.6
AZ70: =AY69*$C$33 -> 216400.68 | BA70: =AY69*$C$32*$C$33 -> 224906.3 | BB70: =AZ69*$C$32*$C$33 -> 233746.23 | BC70: =BA69*$C$32*$C$33 -> 242933.62 | BD70: =BB69*$C$32*$C$33 -> 252482.12 | BE70: =BC69*$C$32*$C$33 -> 262405.92 | BF70: =BD69*$C$32*$C$33 -> 272719.78 | BG70: =BE69*$C$32*$C$33 -> 283439.02 | BH70: =BF69*$C$32*$C$33 -> 294579.58 | ... DC70: =DA69*$C$32*$C$33 -> 1803531.8
BA71: =AZ70*$C$33 -> 208216.73 | BB71: =AZ70*$C$32*$C$33 -> 216400.68 | BC71: =BA70*$C$32*$C$33 -> 224906.3 | BD71: =BB70*$C$32*$C$33 -> 233746.23 | BE71: =BC70*$C$32*$C$33 -> 242933.62 | BF71: =BD70*$C$32*$C$33 -> 252482.12 | BG71: =BE70*$C$32*$C$33 -> 262405.92 | BH71: =BF70*$C$32*$C$33 -> 272719.78 | BI71: =BG70*$C$32*$C$33 -> 283439.02 | ... DC71: =DA70*$C$32*$C$33 -> 1669697.5
BB72: =BA71*$C$33 -> 200342.28 | BC72: =BA71*$C$32*$C$33 -> 208216.73 | BD72: =BB71*$C$32*$C$33 -> 216400.68 | BE72: =BC71*$C$32*$C$33 -> 224906.3 | BF72: =BD71*$C$32*$C$33 -> 233746.23 | BG72: =BE71*$C$32*$C$33 -> 242933.62 | BH72: =BF71*$C$32*$C$33 -> 252482.12 | BI72: =BG71*$C$32*$C$33 -> 262405.92 | BJ72: =BH71*$C$32*$C$33 -> 272719.78 | ... DC72: =DA71*$C$32*$C$33 -> 1545794.6
BC73: =BB72*$C$33 -> 192765.63 | BD73: =BB72*$C$32*$C$33 -> 200342.28 | BE73: =BC72*$C$32*$C$33 -> 208216.73 | BF73: =BD72*$C$32*$C$33 -> 216400.68 | BG73: =BE72*$C$32*$C$33 -> 224906.3 | BH73: =BF72*$C$32*$C$33 -> 233746.23 | BI73: =BG72*$C$32*$C$33 -> 242933.62 | BJ73: =BH72*$C$32*$C$33 -> 252482.12 | BK73: =BI72*$C$32*$C$33 -> 262405.92 | ... DC73: =DA72*$C$32*$C$33 -> 1431086.2
BD74: =BC73*$C$33 -> 185475.52 | BE74: =BC73*$C$32*$C$33 -> 192765.63 | BF74: =BD73*$C$32*$C$33 -> 200342.28 | BG74: =BE73*$C$32*$C$33 -> 208216.73 | BH74: =BF73*$C$32*$C$33 -> 216400.68 | BI74: =BG73*$C$32*$C$33 -> 224906.3 | BJ74: =BH73*$C$32*$C$33 -> 233746.23 | BK74: =BI73*$C$32*$C$33 -> 242933.62 | BL74: =BJ73*$C$32*$C$33 -> 252482.12 | ... DC74: =DA73*$C$32*$C$33 -> 1324889.9
BE75: =BD74*$C$33 -> 178461.11 | BF75: =BD74*$C$32*$C$33 -> 185475.52 | BG75: =BE74*$C$32*$C$33 -> 192765.63 | BH75: =BF74*$C$32*$C$33 -> 200342.28 | BI75: =BG74*$C$32*$C$33 -> 208216.73 | BJ75: =BH74*$C$32*$C$33 -> 216400.68 | BK75: =BI74*$C$32*$C$33 -> 224906.3 | BL75: =BJ74*$C$32*$C$33 -> 233746.23 | BM75: =BK74*$C$32*$C$33 -> 242933.62 | ... DC75: =DA74*$C$32*$C$33 -> 1226574
BF76: =BE75*$C$33 -> 171711.98 | BG76: =BE75*$C$32*$C$33 -> 178461.11 | BH76: =BF75*$C$32*$C$33 -> 185475.52 | BI76: =BG75*$C$32*$C$33 -> 192765.63 | BJ76: =BH75*$C$32*$C$33 -> 200342.28 | BK76: =BI75*$C$32*$C$33 -> 208216.73 | BL76: =BJ75*$C$32*$C$33 -> 216400.68 | BM76: =BK75*$C$32*$C$33 -> 224906.3 | BN76: =BL75*$C$32*$C$33 -> 233746.23 | ... DC76: =DA75*$C$32*$C$33 -> 1135553.9
BG77: =BF76*$C$33 -> 165218.09 | BH77: =BF76*$C$32*$C$33 -> 171711.98 | BI77: =BG76*$C$32*$C$33 -> 178461.11 | BJ77: =BH76*$C$32*$C$33 -> 185475.52 | BK77: =BI76*$C$32*$C$33 -> 192765.63 | BL77: =BJ76*$C$32*$C$33 -> 200342.28 | BM77: =BK76*$C$32*$C$33 -> 208216.73 | BN77: =BL76*$C$32*$C$33 -> 216400.68 | BO77: =BM76*$C$32*$C$33 -> 224906.3 | ... DC77: =DA76*$C$32*$C$33 -> 1051288.1
BH78: =BG77*$C$33 -> 158969.79 | BI78: =BG77*$C$32*$C$33 -> 165218.09 | BJ78: =BH77*$C$32*$C$33 -> 171711.98 | BK78: =BI77*$C$32*$C$33 -> 178461.11 | BL78: =BJ77*$C$32*$C$33 -> 185475.52 | BM78: =BK77*$C$32*$C$33 -> 192765.63 | BN78: =BL77*$C$32*$C$33 -> 200342.28 | BO78: =BM77*$C$32*$C$33 -> 208216.73 | BP78: =BN77*$C$32*$C$33 -> 216400.68 | ... DC78: =DA77*$C$32*$C$33 -> 973275.41
BI79: =BH78*$C$33 -> 152957.78 | BJ79: =BH78*$C$32*$C$33 -> 158969.79 | BK79: =BI78*$C$32*$C$33 -> 165218.09 | BL79: =BJ78*$C$32*$C$33 -> 171711.98 | BM79: =BK78*$C$32*$C$33 -> 178461.11 | BN79: =BL78*$C$32*$C$33 -> 185475.52 | BO79: =BM78*$C$32*$C$33 -> 192765.63 | BP79: =BN78*$C$32*$C$33 -> 200342.28 | BQ79: =BO78*$C$32*$C$33 -> 208216.73 | ... DC79: =DA78*$C$32*$C$33 -> 901051.77
BJ80: =BI79*$C$33 -> 147173.15 | BK80: =BI79*$C$32*$C$33 -> 152957.78 | BL80: =BJ79*$C$32*$C$33 -> 158969.79 | BM80: =BK79*$C$32*$C$33 -> 165218.09 | BN80: =BL79*$C$32*$C$33 -> 171711.98 | BO80: =BM79*$C$32*$C$33 -> 178461.11 | BP80: =BN79*$C$32*$C$33 -> 185475.52 | BQ80: =BO79*$C$32*$C$33 -> 192765.63 | BR80: =BP79*$C$32*$C$33 -> 200342.28 | ... DC80: =DA79*$C$32*$C$33 -> 834187.61
BK81: =BJ80*$C$33 -> 141607.28 | BL81: =BJ80*$C$32*$C$33 -> 147173.15 | BM81: =BK80*$C$32*$C$33 -> 152957.78 | BN81: =BL80*$C$32*$C$33 -> 158969.79 | BO81: =BM80*$C$32*$C$33 -> 165218.09 | BP81: =BN80*$C$32*$C$33 -> 171711.98 | BQ81: =BO80*$C$32*$C$33 -> 178461.11 | BR81: =BP80*$C$32*$C$33 -> 185475.52 | BS81: =BQ80*$C$32*$C$33 -> 192765.63 | ... DC81: =DA80*$C$32*$C$33 -> 772285.23
BL82: =BK81*$C$33 -> 136251.9 | BM82: =BK81*$C$32*$C$33 -> 141607.28 | BN82: =BL81*$C$32*$C$33 -> 147173.15 | BO82: =BM81*$C$32*$C$33 -> 152957.78 | BP82: =BN81*$C$32*$C$33 -> 158969.79 | BQ82: =BO81*$C$32*$C$33 -> 165218.09 | BR82: =BP81*$C$32*$C$33 -> 171711.98 | BS82: =BQ81*$C$32*$C$33 -> 178461.11 | BT82: =BR81*$C$32*$C$33 -> 185475.52 | ... DC82: =DA81*$C$32*$C$33 -> 714976.43
BM83: =BL82*$C$33 -> 131099.06 | BN83: =BL82*$C$32*$C$33 -> 136251.9 | BO83: =BM82*$C$32*$C$33 -> 141607.28 | BP83: =BN82*$C$32*$C$33 -> 147173.15 | BQ83: =BO82*$C$32*$C$33 -> 152957.78 | BR83: =BP82*$C$32*$C$33 -> 158969.79 | BS83: =BQ82*$C$32*$C$33 -> 165218.09 | BT83: =BR82*$C$32*$C$33 -> 171711.98 | BU83: =BS82*$C$32*$C$33 -> 178461.11 | ... DC83: =DA82*$C$32*$C$33 -> 661920.32
BN84: =BM83*$C$33 -> 126141.09 | BO84: =BM83*$C$32*$C$33 -> 131099.06 | BP84: =BN83*$C$32*$C$33 -> 136251.9 | BQ84: =BO83*$C$32*$C$33 -> 141607.28 | BR84: =BP83*$C$32*$C$33 -> 147173.15 | BS84: =BQ83*$C$32*$C$33 -> 152957.78 | BT84: =BR83*$C$32*$C$33 -> 158969.79 | BU84: =BS83*$C$32*$C$33 -> 165218.09 | BV84: =BT83*$C$32*$C$33 -> 171711.98 | ... DC84: =DA83*$C$32*$C$33 -> 612801.34
BO85: =BN84*$C$33 -> 121370.62 | BP85: =BN84*$C$32*$C$33 -> 126141.09 | BQ85: =BO84*$C$32*$C$33 -> 131099.06 | BR85: =BP84*$C$32*$C$33 -> 136251.9 | BS85: =BQ84*$C$32*$C$33 -> 141607.28 | BT85: =BR84*$C$32*$C$33 -> 147173.15 | BU85: =BS84*$C$32*$C$33 -> 152957.78 | BV85: =BT84*$C$32*$C$33 -> 158969.79 | BW85: =BU84*$C$32*$C$33 -> 165218.09 | ... DC85: =DA84*$C$32*$C$33 -> 567327.32
BP86: =BO85*$C$33 -> 116780.56 | BQ86: =BO85*$C$32*$C$33 -> 121370.62 | BR86: =BP85*$C$32*$C$33 -> 126141.09 | BS86: =BQ85*$C$32*$C$33 -> 131099.06 | BT86: =BR85*$C$32*$C$33 -> 136251.9 | BU86: =BS85*$C$32*$C$33 -> 141607.28 | BV86: =BT85*$C$32*$C$33 -> 147173.15 | BW86: =BU85*$C$32*$C$33 -> 152957.78 | BX86: =BV85*$C$32*$C$33 -> 158969.79 | ... DC86: =DA85*$C$32*$C$33 -> 525227.79
BQ87: =BP86*$C$33 -> 112364.09 | BR87: =BP86*$C$32*$C$33 -> 116780.56 | BS87: =BQ86*$C$32*$C$33 -> 121370.62 | BT87: =BR86*$C$32*$C$33 -> 126141.09 | BU87: =BS86*$C$32*$C$33 -> 131099.06 | BV87: =BT86*$C$32*$C$33 -> 136251.9 | BW87: =BU86*$C$32*$C$33 -> 141607.28 | BX87: =BV86*$C$32*$C$33 -> 147173.15 | BY87: =BW86*$C$32*$C$33 -> 152957.78 | ... DC87: =DA86*$C$32*$C$33 -> 486252.32
BR88: =BQ87*$C$33 -> 108114.65 | BS88: =BQ87*$C$32*$C$33 -> 112364.09 | BT88: =BR87*$C$32*$C$33 -> 116780.56 | BU88: =BS87*$C$32*$C$33 -> 121370.62 | BV88: =BT87*$C$32*$C$33 -> 126141.09 | BW88: =BU87*$C$32*$C$33 -> 131099.06 | BX88: =BV87*$C$32*$C$33 -> 136251.9 | BY88: =BW87*$C$32*$C$33 -> 141607.28 | BZ88: =BX87*$C$32*$C$33 -> 147173.15 | ... DC88: =DA87*$C$32*$C$33 -> 450169.1
BS89: =BR88*$C$33 -> 104025.92 | BT89: =BR88*$C$32*$C$33 -> 108114.65 | BU89: =BS88*$C$32*$C$33 -> 112364.09 | BV89: =BT88*$C$32*$C$33 -> 116780.56 | BW89: =BU88*$C$32*$C$33 -> 121370.62 | BX89: =BV88*$C$32*$C$33 -> 126141.09 | BY89: =BW88*$C$32*$C$33 -> 131099.06 | BZ89: =BX88*$C$32*$C$33 -> 136251.9 | CA89: =BY88*$C$32*$C$33 -> 141607.28 | ... DC89: =DA88*$C$32*$C$33 -> 416763.5
BT90: =BS89*$C$33 -> 100091.81 | BU90: =BS89*$C$32*$C$33 -> 104025.92 | BV90: =BT89*$C$32*$C$33 -> 108114.65 | BW90: =BU89*$C$32*$C$33 -> 112364.09 | BX90: =BV89*$C$32*$C$33 -> 116780.56 | BY90: =BW89*$C$32*$C$33 -> 121370.62 | BZ90: =BX89*$C$32*$C$33 -> 126141.09 | CA90: =BY89*$C$32*$C$33 -> 131099.06 | CB90: =BZ89*$C$32*$C$33 -> 136251.9 | ... DC90: =DA89*$C$32*$C$33 -> 385836.82
BU91: =BT90*$C$33 -> 96306.487 | BV91: =BT90*$C$32*$C$33 -> 100091.81 | BW91: =BU90*$C$32*$C$33 -> 104025.92 | BX91: =BV90*$C$32*$C$33 -> 108114.65 | BY91: =BW90*$C$32*$C$33 -> 112364.09 | BZ91: =BX90*$C$32*$C$33 -> 116780.56 | CA91: =BY90*$C$32*$C$33 -> 121370.62 | CB91: =BZ90*$C$32*$C$33 -> 126141.09 | CC91: =CA90*$C$32*$C$33 -> 131099.06 | ... DC91: =DA90*$C$32*$C$33 -> 357205.11
BV92: =BU91*$C$33 -> 92664.319 | BW92: =BU91*$C$32*$C$33 -> 96306.487 | BX92: =BV91*$C$32*$C$33 -> 100091.81 | BY92: =BW91*$C$32*$C$33 -> 104025.92 | BZ92: =BX91*$C$32*$C$33 -> 108114.65 | CA92: =BY91*$C$32*$C$33 -> 112364.09 | CB92: =BZ91*$C$32*$C$33 -> 116780.56 | CC92: =CA91*$C$32*$C$33 -> 121370.62 | CD92: =CB91*$C$32*$C$33 -> 126141.09 | ... DC92: =DA91*$C$32*$C$33 -> 330698.06
BW93: =BV92*$C$33 -> 89159.893 | BX93: =BV92*$C$32*$C$33 -> 92664.319 | BY93: =BW92*$C$32*$C$33 -> 96306.487 | BZ93: =BX92*$C$32*$C$33 -> 100091.81 | CA93: =BY92*$C$32*$C$33 -> 104025.92 | CB93: =BZ92*$C$32*$C$33 -> 108114.65 | CC93: =CA92*$C$32*$C$33 -> 112364.09 | CD93: =CB92*$C$32*$C$33 -> 116780.56 | CE93: =CC92*$C$32*$C$33 -> 121370.62 | ... DC93: =DA92*$C$32*$C$33 -> 306158.02
BX94: =BW93*$C$33 -> 85787.998 | BY94: =BW93*$C$32*$C$33 -> 89159.893 | BZ94: =BX93*$C$32*$C$33 -> 92664.319 | CA94: =BY93*$C$32*$C$33 -> 96306.487 | CB94: =BZ93*$C$32*$C$33 -> 100091.81 | CC94: =CA93*$C$32*$C$33 -> 104025.92 | CD94: =CB93*$C$32*$C$33 -> 108114.65 | CE94: =CC93*$C$32*$C$33 -> 112364.09 | CF94: =CD93*$C$32*$C$33 -> 116780.56 | ... DC94: =DA93*$C$32*$C$33 -> 283439.02
BY95: =BX94*$C$33 -> 82543.624 | BZ95: =BX94*$C$32*$C$33 -> 85787.998 | CA95: =BY94*$C$32*$C$33 -> 89159.893 | CB95: =BZ94*$C$32*$C$33 -> 92664.319 | CC95: =CA94*$C$32*$C$33 -> 96306.487 | CD95: =CB94*$C$32*$C$33 -> 100091.81 | CE95: =CC94*$C$32*$C$33 -> 104025.92 | CF95: =CD94*$C$32*$C$33 -> 108114.65 | CG95: =CE94*$C$32*$C$33 -> 112364.09 | ... DC95: =DA94*$C$32*$C$33 -> 262405.92
BZ96: =BY95*$C$33 -> 79421.946 | CA96: =BY95*$C$32*$C$33 -> 82543.624 | CB96: =BZ95*$C$32*$C$33 -> 85787.998 | CC96: =CA95*$C$32*$C$33 -> 89159.893 | CD96: =CB95*$C$32*$C$33 -> 92664.319 | CE96: =CC95*$C$32*$C$33 -> 96306.487 | CF96: =CD95*$C$32*$C$33 -> 100091.81 | CG96: =CE95*$C$32*$C$33 -> 104025.92 | CH96: =CF95*$C$32*$C$33 -> 108114.65 | ... DC96: =DA95*$C$32*$C$33 -> 242933.62
CA97: =BZ96*$C$33 -> 76418.327 | CB97: =BZ96*$C$32*$C$33 -> 79421.946 | CC97: =CA96*$C$32*$C$33 -> 82543.624 | CD97: =CB96*$C$32*$C$33 -> 85787.998 | CE97: =CC96*$C$32*$C$33 -> 89159.893 | CF97: =CD96*$C$32*$C$33 -> 92664.319 | CG97: =CE96*$C$32*$C$33 -> 96306.487 | CH97: =CF96*$C$32*$C$33 -> 100091.81 | CI97: =CG96*$C$32*$C$33 -> 104025.92 | ... DC97: =DA96*$C$32*$C$33 -> 224906.3
CB98: =CA97*$C$33 -> 73528.299 | CC98: =CA97*$C$32*$C$33 -> 76418.327 | CD98: =CB97*$C$32*$C$33 -> 79421.946 | CE98: =CC97*$C$32*$C$33 -> 82543.624 | CF98: =CD97*$C$32*$C$33 -> 85787.998 | CG98: =CE97*$C$32*$C$33 -> 89159.893 | CH98: =CF97*$C$32*$C$33 -> 92664.319 | CI98: =CG97*$C$32*$C$33 -> 96306.487 | CJ98: =CH97*$C$32*$C$33 -> 100091.81 | ... DC98: =DA97*$C$32*$C$33 -> 208216.73
CC99: =CB98*$C$33 -> 70747.568 | CD99: =CB98*$C$32*$C$33 -> 73528.299 | CE99: =CC98*$C$32*$C$33 -> 76418.327 | CF99: =CD98*$C$32*$C$33 -> 79421.946 | CG99: =CE98*$C$32*$C$33 -> 82543.624 | CH99: =CF98*$C$32*$C$33 -> 85787.998 | CI99: =CG98*$C$32*$C$33 -> 89159.893 | CJ99: =CH98*$C$32*$C$33 -> 92664.319 | CK99: =CI98*$C$32*$C$33 -> 96306.487 | ... DC99: =DA98*$C$32*$C$33 -> 192765.63
CD100: =CC99*$C$33 -> 68072 | CE100: =CC99*$C$32*$C$33 -> 70747.568 | CF100: =CD99*$C$32*$C$33 -> 73528.299 | CG100: =CE99*$C$32*$C$33 -> 76418.327 | CH100: =CF99*$C$32*$C$33 -> 79421.946 | CI100: =CG99*$C$32*$C$33 -> 82543.624 | CJ100: =CH99*$C$32*$C$33 -> 85787.998 | CK100: =CI99*$C$32*$C$33 -> 89159.893 | CL100: =CJ99*$C$32*$C$33 -> 92664.319 | ... DC100: =DA99*$C$32*$C$33 -> 178461.11
CE101: =CD100*$C$33 -> 65497.618 | CF101: =CD100*$C$32*$C$33 -> 68072 | CG101: =CE100*$C$32*$C$33 -> 70747.568 | CH101: =CF100*$C$32*$C$33 -> 73528.299 | CI101: =CG100*$C$32*$C$33 -> 76418.327 | CJ101: =CH100*$C$32*$C$33 -> 79421.946 | CK101: =CI100*$C$32*$C$33 -> 82543.624 | CL101: =CJ100*$C$32*$C$33 -> 85787.998 | CM101: =CK100*$C$32*$C$33 -> 89159.893 | ... DC101: =DA100*$C$32*$C$33 -> 165218.09
...

Sheet Straight Debt
B2: Straight Debt
B3: Valuation Date | C3: =Input!C2 -> 45838
B5: Risky Rate:
B6: ='Risky Rate'!B3 -> Rfr | C6: ='Risky Rate'!C3 -> 0.039623726
B7: ='Risky Rate'!B4 -> OAS | C7: ='Risky Rate'!C4 -> 0.14850175
B8: ='Risky Rate'!B5 -> Liquidity | C8: ='Risky Rate'!C5 -> 0.015
B9: ='Risky Rate'!B6 -> Other Risk | C9: ='Risky Rate'!C6 -> 0.28763281
B10: Total | C10: =SUM(C6:C9) -> 0.49075828
B13: Date | C13: Interest Payment | D13: Principal Repayment | E13: TTM | F13: PV
B14: =Input!B16 -> 45291
B15: =Input!B17 -> 45657
B16: =Input!B18 -> 46022 | C16: =Input!C18 -> 1000000 | E16: =YEARFRAC(B16,$C$3,3) -> 0.50410959 | F16: =SUM(C16:D16)/(1+$C$10)^E16 -> 817680.71
B17: =Input!B19 -> 46217 | C17: =Input!C19 -> 534246.58 | D17: =Input!C4 -> 10000000 | E17: =YEARFRAC(B17,$C$3,3) -> 1.0383562 | F17: =SUM(C17:D17)/(1+$C$10)^E17 -> 6958970.8
B18: Total PV | F18: =ROUND(SUM(F14:F17),-4) -> 7780000

Sheet Input
B2: Valuation Date | C2: =DATE(2025,6,30) -> 45838
B3: Issue Date | C3: =DATE(2023,7,14) -> 45121
B4: Principal | C4: 10000000 | D4: USD (4mil+6mil)
B5: Conversion Securities | C5: Series B Preferred Membershup Units
B6: Conversion Price | C6: 5484545.2 | D6: USD
B7: Day Basis | C7: Actual/365
B8: Maturity Date | C8: =EDATE(C3,36) -> 46217 | D8: May be extended by up to 12 months
B9: Extended Maturity Date | C9: =EDATE(C8,12) -> 46582
B10: Interest Rate | C10: 0.1 | D10: Payable annually in arrear on 31 Dec of each calendar year. All outstanding accrued interest (1 Jan 2026 to 14 July 2026) shall be payable on maturity date
B11: Prepayment | C11: May not be made without consent of Holder
B12: Conversion | C12: Prior to maturity date
B13: Probability for Extension | C13: 0.7 | D13: Assumed by the Client after discussion with the issuer
B15: Interest Payment Schedule (No Extension):
B16: =DATE(2023,12,31) -> 45291 | C16: =C$4*$C$10*YEARFRAC(B16,$C$3,3) -> 465753.42
B17: =EDATE(B16,12) -> 45657 | C17: =C$4*$C$10*YEARFRAC(B17,B16,3) -> 1002739.7
B18: =EDATE(B17,12) -> 46022 | C18: =C$4*$C$10*YEARFRAC(B18,B17,3) -> 1000000
B19: =C8 -> 46217 | C19: =C$4*$C$10*YEARFRAC(B19,B18,3) -> 534246.58
B21: Interest Payment Schedule (Extension):
B22: =B16 -> 45291 | C22: =C$4*$C$10*YEARFRAC(B22,$C$3,3) -> 465753.42
B23: =B17 -> 45657 | C23: =C$4*$C$10*YEARFRAC(B23,B22,3) -> 1002739.7
B24: =B18 -> 46022 | C24: =C$4*$C$10*YEARFRAC(B24,B23,3) -> 1000000
B25: =EDATE(B24,12) -> 46387 | C25: =C$4*$C$10*YEARFRAC(B25,B24,3) -> 1000000
B26: =C9 -> 46582 | C26: =C$4*$C$10*YEARFRAC(B26,B25,3) -> 534246.58

Sheet Full CB_Extend
B2: Full CB | G2: Date | H2: =C5 -> 45121 | I2: {=TRANSPOSE(Input!B22:B26)} -> 45291 | J2: 45657 | K2: 46022 | L2: 46387 | M2: 46582
B3: Valuation Date | C3: =Input!C2 -> 45838
G4: Steps | K4: =ROUNDDOWN(YEARFRAC(K2,$C$3,3)/$C$30,0)+1 -> 25 | L4: =ROUNDDOWN(YEARFRAC(L2,$C$3,3)/$C$30,0)+1 -> 74 | M4: =C29 -> 100
B5: Issue Date | C5: =Input!C3 -> 45121 | D5: =C5 -> 45121 | G5: Interest Payment | K5: =Input!C24 -> 1000000 | L5: =Input!C25 -> 1000000 | M5: =Input!C26 -> 534246.58
B6: Extended Maturity Date | C6: =Input!C9 -> 46582 | D6: =C6 -> 46582
B7: State Date of Conversion Period | C7: =C5 -> 45121 | D7: =C7 -> 45121
B8: End Date of Conversion Period | C8: =C6 -> 46582 | D8: =C8 -> 46582
B9: Spot Price of Series B Preferred Membership Units | C9: 1226574 | D9: Based on allocation as at 2025/6/30
B10: Strike Price (USD) | C10: =Input!C6 -> 5484545.2
B11: Discount Rate (Annual) | C11: ='Risky Rate'!D7 -> 0.48833267
B12: Discount Rate (Cont.) | C12: =LN(1+C11) -> 0.39765648
B13: Risk-free Rate (Annual) | C13: ='Risky Rate'!D3 -> 0.03719811
B14: Risk-free Rate (Cont.) | C14: =LN(1+C13) -> 0.036522952
B15: Volatility | C15: =Vol!G26 -> 0.36458111
B16: Dividend Yield | C16: 0
B17: Bond Life (year) | C17: =YEARFRAC(C3,C6,3) -> 2.0383562
B18: Redemption Premium (Maturity) | C18: 1
B19: Coupon | C19: 0.1
B20: Accrued Interest (USD) | C20: =C22*C19*YEARFRAC(C21,C3,3) -> 495890.41
B21: Last Coupon Payment Date | C21: =DATE(2024,12,31) -> 45657 | G21: 0 | H21: 1 | I21: 2 | J21: 3 | K21: 4 | L21: 5 | M21: 6 | N21: 7 | O21: 8 | P21: 9 | Q21: 10 | R21: 11 | S21: 12 | T21: 13 | U21: 14 | V21: 15 | W21: 16 | X21: 17 | Y21: 18 | Z21: 19 | AA21: 20 | AB21: 21 | AC21: 22 | AD21: 23 | AE21: 24 | AF21: 25 | AG21: 26 | AH21: 27 | AI21: 28 | AJ21: 29 | AK21: 30 | AL21: 31 | AM21: 32 | AN21: 33 | AO21: 34 | AP21: 35 | AQ21: 36 | AR21: 37 | AS21: 38 | AT21: 39 | AU21: 40 | AV21: 41 | AW21: 42 | AX21: 43 | AY21: 44 | AZ21: 45 | BA21: 46 | BB21: 47 | BC21: 48 | BD21: 49 | BE21: 50 | BF21: 51 | BG21: 52 | BH21: 53 | BI21: 54 | BJ21: 55 | BK21: 56 | BL21: 57 | BM21: 58 | BN21: 59 | BO21: 60 | BP21: 61 | BQ21: 62 | BR21: 63 | BS21: 64 | BT21: 65 | BU21: 66 | BV21: 67 | BW21: 68 | BX21: 69 | BY21: 70 | BZ21: 71 | CA21: 72 | CB21: 73 | CC21: 74 | CD21: 75 | CE21: 76 | CF21: 77 | CG21: 78 | CH21: 79 | CI21: 80 | CJ21: 81 | CK21: 82 | CL21: 83 | CM21: 84 | CN21: 85 | CO21: 86 | CP21: 87 | CQ21: 88 | CR21: 89 | CS21: 90 | CT21: 91 | CU21: 92 | CV21: 93 | CW21: 94 | CX21: 95 | CY21: 96 | CZ21: 97 | DA21: 98 | DB21: 99 | DC21: 100
B22: Outstanding Principal of CB (USD) | C22: =Input!C4 -> 10000000 | E22: Date | G22: =$C$3 -> 45838 | H22: =$G$22+($C$6-$C$3)/$C$29*H21 -> 45845.44 | I22: =$G$22+($C$6-$C$3)/$C$29*I21 -> 45852.88 | J22: =$G$22+($C$6-$C$3)/$C$29*J21 -> 45860.32 | K22: =$G$22+($C$6-$C$3)/$C$29*K21 -> 45867.76 | L22: =$G$22+($C$6-$C$3)/$C$29*L21 -> 45875.2 | M22: =$G$22+($C$6-$C$3)/$C$29*M21 -> 45882.64 | N22: =$G$22+($C$6-$C$3)/$C$29*N21 -> 45890.08 | O22: =$G$22+($C$6-$C$3)/$C$29*O21 -> 45897.52 | ... DC22: =$G$22+($C$6-$C$3)/$C$29*DC21 -> 46582
B23: No. of Options | C23: =C22/C10 -> 1.8233052 | E23: No. of Years | G23: =YEARFRAC($G$22,G22,0) -> 0 | H23: =YEARFRAC($G$22,H22,0) -> 0.019444444 | I23: =YEARFRAC($G$22,I22,0) -> 0.038888889 | J23: =YEARFRAC($G$22,J22,0) -> 0.061111111 | K23: =YEARFRAC($G$22,K22,0) -> 0.080555556 | L23: =YEARFRAC($G$22,L22,0) -> 0.1 | M23: =YEARFRAC($G$22,M22,0) -> 0.11944444 | N23: =YEARFRAC($G$22,N22,0) -> 0.14166667 | ... DC23: =YEARFRAC($G$22,DC22,0) -> 2.0388889
B24: Oustanding Number of Shares | C24: 68.773706
B25: Total Principal Outstanding (USD) | C25: =C22 -> 10000000 | E25: Stock Price Binomial Tree | G25: =C9 -> 1226574 | H25: =G25*$C$32 -> 1292110 | I25: =H25*$C$32 -> 1361147.6 | J25: =I25*$C$32 -> 1433873.9 | K25: =J25*$C$32 -> 1510485.9 | L25: =K25*$C$32 -> 1591191.4 | M25: =L25*$C$32 -> 1676208.9 | N25: =M25*$C$32 -> 1765768.9 | O25: =N25*$C$32 -> 1860114.2 | ... DC25: =DB25*$C$32 -> 2.234944e+08
B26: Total No. of Shares to be Issued | C26: =C25/C10 -> 1.8233052 | H26: =G25*$C$33 -> 1164362 | I26: =G25*$C$32*$C$33 -> 1226574 | J26: =H25*$C$32*$C$33 -> 1292110 | K26: =I25*$C$32*$C$33 -> 1361147.6 | L26: =J25*$C$32*$C$33 -> 1433873.9 | M26: =K25*$C$32*$C$33 -> 1510485.9 | N26: =L25*$C$32*$C$33 -> 1591191.4 | O26: =M25*$C$32*$C$33 -> 1676208.9 | P26: =N25*$C$32*$C$33 -> 1765768.9 | ... DC26: =DA25*$C$32*$C$33 -> 2.0139801e+08
B27: Dilution Effect | C27: 1 | I27: =H26*$C$33 -> 1105305.5 | J27: =H26*$C$32*$C$33 -> 1164362 | K27: =I26*$C$32*$C$33 -> 1226574 | L27: =J26*$C$32*$C$33 -> 1292110 | M27: =K26*$C$32*$C$33 -> 1361147.6 | N27: =L26*$C$32*$C$33 -> 1433873.9 | O27: =M26*$C$32*$C$33 -> 1510485.9 | P27: =N26*$C$32*$C$33 -> 1591191.4 | Q27: =O26*$C$32*$C$33 -> 1676208.9 | ... DC27: =DA26*$C$32*$C$33 -> 1.8148625e+08
J28: =I27*$C$33 -> 1049244.2 | K28: =I27*$C$32*$C$33 -> 1105305.5 | L28: =J27*$C$32*$C$33 -> 1164362 | M28: =K27*$C$32*$C$33 -> 1226574 | N28: =L27*$C$32*$C$33 -> 1292110 | O28: =M27*$C$32*$C$33 -> 1361147.6 | P28: =N27*$C$32*$C$33 -> 1433873.9 | Q28: =O27*$C$32*$C$33 -> 1510485.9 | R28: =P27*$C$32*$C$33 -> 1591191.4 | ... DC28: =DA27*$C$32*$C$33 -> 1.6354312e+08
B29: Steps | C29: 100 | K29: =J28*$C$33 -> 996026.41 | L29: =J28*$C$32*$C$33 -> 1049244.2 | M29: =K28*$C$32*$C$33 -> 1105305.5 | N29: =L28*$C$32*$C$33 -> 1164362 | O29: =M28*$C$32*$C$33 -> 1226574 | P29: =N28*$C$32*$C$33 -> 1292110 | Q29: =O28*$C$32*$C$33 -> 1361147.6 | R29: =P28*$C$32*$C$33 -> 1433873.9 | S29: =Q28*$C$32*$C$33 -> 1510485.9 | ... DC29: =DA28*$C$32*$C$33 -> 1.4737398e+08
B30: Delta | C30: =C17/C29 -> 0.020383562 | L30: =K29*$C$33 -> 945507.82 | M30: =K29*$C$32*$C$33 -> 996026.41 | N30: =L29*$C$32*$C$33 -> 1049244.2 | O30: =M29*$C$32*$C$33 -> 1105305.5 | P30: =N29*$C$32*$C$33 -> 1164362 | Q30: =O29*$C$32*$C$33 -> 1226574 | R30: =P29*$C$32*$C$33 -> 1292110 | S30: =Q29*$C$32*$C$33 -> 1361147.6 | T30: =R29*$C$32*$C$33 -> 1433873.9 | ... DC30: =DA29*$C$32*$C$33 -> 1.3280345e+08
M31: =L30*$C$33 -> 897551.54 | N31: =L30*$C$32*$C$33 -> 945507.82 | O31: =M30*$C$32*$C$33 -> 996026.41 | P31: =N30*$C$32*$C$33 -> 1049244.2 | Q31: =O30*$C$32*$C$33 -> 1105305.5 | R31: =P30*$C$32*$C$33 -> 1164362 | S31: =Q30*$C$32*$C$33 -> 1226574 | T31: =R30*$C$32*$C$33 -> 1292110 | U31: =S30*$C$32*$C$33 -> 1361147.6 | ... DC31: =DA30*$C$32*$C$33 -> 1.1967347e+08
B32: U | C32: =EXP(C15*SQRT(C30)) -> 1.0534301 | N32: =M31*$C$33 -> 852027.61 | O32: =M31*$C$32*$C$33 -> 897551.54 | P32: =N31*$C$32*$C$33 -> 945507.82 | Q32: =O31*$C$32*$C$33 -> 996026.41 | R32: =P31*$C$32*$C$33 -> 1049244.2 | S32: =Q31*$C$32*$C$33 -> 1105305.5 | T32: =R31*$C$32*$C$33 -> 1164362 | U32: =S31*$C$32*$C$33 -> 1226574 | V32: =T31*$C$32*$C$33 -> 1292110 | ... DC32: =DA31*$C$32*$C$33 -> 1.0784163e+08
B33: D | C33: =1/C32 -> 0.94927987 | O33: =N32*$C$33 -> 808812.66 | P33: =N32*$C$32*$C$33 -> 852027.61 | Q33: =O32*$C$32*$C$33 -> 897551.54 | R33: =P32*$C$32*$C$33 -> 945507.82 | S33: =Q32*$C$32*$C$33 -> 996026.41 | T33: =R32*$C$32*$C$33 -> 1049244.2 | U33: =S32*$C$32*$C$33 -> 1105305.5 | V33: =T32*$C$32*$C$33 -> 1164362 | W33: =U32*$C$32*$C$33 -> 1226574 | ... DC33: =DA32*$C$32*$C$33 -> 97179572
B34: P | C34: =(EXP((C14-C16)*C30)-C33)/(C32-C33) -> 0.49414071 | P34: =O33*$C$33 -> 767789.58 | Q34: =O33*$C$32*$C$33 -> 808812.66 | R34: =P33*$C$32*$C$33 -> 852027.61 | S34: =Q33*$C$32*$C$33 -> 897551.54 | T34: =R33*$C$32*$C$33 -> 945507.82 | U34: =S33*$C$32*$C$33 -> 996026.41 | V34: =T33*$C$32*$C$33 -> 1049244.2 | W34: =U33*$C$32*$C$33 -> 1105305.5 | X34: =V33*$C$32*$C$33 -> 1164362 | ... DC34: =DA33*$C$32*$C$33 -> 87571648
B35: 1-P | C35: =1-C34 -> 0.50585929 | Q35: =P34*$C$33 -> 728847.19 | R35: =P34*$C$32*$C$33 -> 767789.58 | S35: =Q34*$C$32*$C$33 -> 808812.66 | T35: =R34*$C$32*$C$33 -> 852027.61 | U35: =S34*$C$32*$C$33 -> 897551.54 | V35: =T34*$C$32*$C$33 -> 945507.82 | W35: =U34*$C$32*$C$33 -> 996026.41 | X35: =V34*$C$32*$C$33 -> 1049244.2 | Y35: =W34*$C$32*$C$33 -> 1105305.5 | ... DC35: =DA34*$C$32*$C$33 -> 78913638
R36: =Q35*$C$33 -> 691879.96 | S36: =Q35*$C$32*$C$33 -> 728847.19 | T36: =R35*$C$32*$C$33 -> 767789.58 | U36: =S35*$C$32*$C$33 -> 808812.66 | V36: =T35*$C$32*$C$33 -> 852027.61 | W36: =U35*$C$32*$C$33 -> 897551.54 | X36: =V35*$C$32*$C$33 -> 945507.82 | Y36: =W35*$C$32*$C$33 -> 996026.41 | Z36: =X35*$C$32*$C$33 -> 1049244.2 | ... DC36: =DA35*$C$32*$C$33 -> 71111626
B37: Total CB Value (HK$) | C37: =ROUND(G238+G345,-4) -> 6060000 | S37: =R36*$C$33 -> 656787.72 | T37: =R36*$C$32*$C$33 -> 691879.96 | U37: =S36*$C$32*$C$33 -> 728847.19 | V37: =T36*$C$32*$C$33 -> 767789.58 | W37: =U36*$C$32*$C$33 -> 808812.66 | X37: =V36*$C$32*$C$33 -> 852027.61 | Y37: =W36*$C$32*$C$33 -> 897551.54 | Z37: =X36*$C$32*$C$33 -> 945507.82 | AA37: =Y36*$C$32*$C$33 -> 996026.41 | ... DC37: =DA36*$C$32*$C$33 -> 64080981
T38: =S37*$C$33 -> 623475.36 | U38: =S37*$C$32*$C$33 -> 656787.72 | V38: =T37*$C$32*$C$33 -> 691879.96 | W38: =U37*$C$32*$C$33 -> 728847.19 | X38: =V37*$C$32*$C$33 -> 767789.58 | Y38: =W37*$C$32*$C$33 -> 808812.66 | Z38: =X37*$C$32*$C$33 -> 852027.61 | AA38: =Y37*$C$32*$C$33 -> 897551.54 | AB38: =Z37*$C$32*$C$33 -> 945507.82 | ... DC38: =DA37*$C$32*$C$33 -> 57745440
C39: =C37-C22 -> -3940000 | U39: =T38*$C$33 -> 591852.61 | V39: =T38*$C$32*$C$33 -> 623475.36 | W39: =U38*$C$32*$C$33 -> 656787.72 | X39: =V38*$C$32*$C$33 -> 691879.96 | Y39: =W38*$C$32*$C$33 -> 728847.19 | Z39: =X38*$C$32*$C$33 -> 767789.58 | AA39: =Y38*$C$32*$C$33 -> 808812.66 | AB39: =Z38*$C$32*$C$33 -> 852027.61 | AC39: =AA38*$C$32*$C$33 -> 897551.54 | ... DC39: =DA38*$C$32*$C$33 -> 52036279
V40: =U39*$C$33 -> 561833.77 | W40: =U39*$C$32*$C$33 -> 591852.61 | X40: =V39*$C$32*$C$33 -> 623475.36 | Y40: =W39*$C$32*$C$33 -> 656787.72 | Z40: =X39*$C$32*$C$33 -> 691879.96 | AA40: =Y39*$C$32*$C$33 -> 728847.19 | AB40: =Z39*$C$32*$C$33 -> 767789.58 | AC40: =AA39*$C$32*$C$33 -> 808812.66 | AD40: =AB39*$C$32*$C$33 -> 852027.61 | ... DC40: =DA39*$C$32*$C$33 -> 46891571
W41: =V40*$C$33 -> 533337.49 | X41: =V40*$C$32*$C$33 -> 561833.77 | Y41: =W40*$C$32*$C$33 -> 591852.61 | Z41: =X40*$C$32*$C$33 -> 623475.36 | AA41: =Y40*$C$32*$C$33 -> 656787.72 | AB41: =Z40*$C$32*$C$33 -> 691879.96 | AC41: =AA40*$C$32*$C$33 -> 728847.19 | AD41: =AB40*$C$32*$C$33 -> 767789.58 | AE41: =AC40*$C$32*$C$33 -> 808812.66 | ... DC41: =DA40*$C$32*$C$33 -> 42255507
X42: =W41*$C$33 -> 506286.54 | Y42: =W41*$C$32*$C$33 -> 533337.49 | Z42: =X41*$C$32*$C$33 -> 561833.77 | AA42: =Y41*$C$32*$C$33 -> 591852.61 | AB42: =Z41*$C$32*$C$33 -> 623475.36 | AC42: =AA41*$C$32*$C$33 -> 656787.72 | AD42: =AB41*$C$32*$C$33 -> 691879.96 | AE42: =AC41*$C$32*$C$33 -> 728847.19 | AF42: =AD41*$C$32*$C$33 -> 767789.58 | ... DC42: =DA41*$C$32*$C$33 -> 38077801
Y43: =X42*$C$33 -> 480607.62 | Z43: =X42*$C$32*$C$33 -> 506286.54 | AA43: =Y42*$C$32*$C$33 -> 533337.49 | AB43: =Z42*$C$32*$C$33 -> 561833.77 | AC43: =AA42*$C$32*$C$33 -> 591852.61 | AD43: =AB42*$C$32*$C$33 -> 623475.36 | AE43: =AC42*$C$32*$C$33 -> 656787.72 | AF43: =AD42*$C$32*$C$33 -> 691879.96 | AG43: =AE42*$C$32*$C$33 -> 728847.19 | ... DC43: =DA42*$C$32*$C$33 -> 34313136
Z44: =Y43*$C$33 -> 456231.14 | AA44: =Y43*$C$32*$C$33 -> 480607.62 | AB44: =Z43*$C$32*$C$33 -> 506286.54 | AC44: =AA43*$C$32*$C$33 -> 533337.49 | AD44: =AB43*$C$32*$C$33 -> 561833.77 | AE44: =AC43*$C$32*$C$33 -> 591852.61 | AF44: =AD43*$C$32*$C$33 -> 623475.36 | AG44: =AE43*$C$32*$C$33 -> 656787.72 | AH44: =AF43*$C$32*$C$33 -> 691879.96 | ... DC44: =DA43*$C$32*$C$33 -> 30920674
AA45: =Z44*$C$33 -> 433091.04 | AB45: =Z44*$C$32*$C$33 -> 456231.14 | AC45: =AA44*$C$32*$C$33 -> 480607.62 | AD45: =AB44*$C$32*$C$33 -> 506286.54 | AE45: =AC44*$C$32*$C$33 -> 533337.49 | AF45: =AD44*$C$32*$C$33 -> 561833.77 | AG45: =AE44*$C$32*$C$33 -> 591852.61 | AH45: =AF44*$C$32*$C$33 -> 623475.36 | AI45: =AG44*$C$32*$C$33 -> 656787.72 | ... DC45: =DA44*$C$32*$C$33 -> 27863617
AB46: =AA45*$C$33 -> 411124.6 | AC46: =AA45*$C$32*$C$33 -> 433091.04 | AD46: =AB45*$C$32*$C$33 -> 456231.14 | AE46: =AC45*$C$32*$C$33 -> 480607.62 | AF46: =AD45*$C$32*$C$33 -> 506286.54 | AG46: =AE45*$C$32*$C$33 -> 533337.49 | AH46: =AF45*$C$32*$C$33 -> 561833.77 | AI46: =AG45*$C$32*$C$33 -> 591852.61 | AJ46: =AH45*$C$32*$C$33 -> 623475.36 | ... DC46: =DA45*$C$32*$C$33 -> 25108804
AC47: =AB46*$C$33 -> 390272.31 | AD47: =AB46*$C$32*$C$33 -> 411124.6 | AE47: =AC46*$C$32*$C$33 -> 433091.04 | AF47: =AD46*$C$32*$C$33 -> 456231.14 | AG47: =AE46*$C$32*$C$33 -> 480607.62 | AH47: =AF46*$C$32*$C$33 -> 506286.54 | AI47: =AG46*$C$32*$C$33 -> 533337.49 | AJ47: =AH46*$C$32*$C$33 -> 561833.77 | AK47: =AI46*$C$32*$C$33 -> 591852.61 | ... DC47: =DA46*$C$32*$C$33 -> 22626354
AD48: =AC47*$C$33 -> 370477.65 | AE48: =AC47*$C$32*$C$33 -> 390272.31 | AF48: =AD47*$C$32*$C$33 -> 411124.6 | AG48: =AE47*$C$32*$C$33 -> 433091.04 | AH48: =AF47*$C$32*$C$33 -> 456231.14 | AI48: =AG47*$C$32*$C$33 -> 480607.62 | AJ48: =AH47*$C$32*$C$33 -> 506286.54 | AK48: =AI47*$C$32*$C$33 -> 533337.49 | AL48: =AJ47*$C$32*$C$33 -> 561833.77 | ... DC48: =DA47*$C$32*$C$33 -> 20389338
AE49: =AD48*$C$33 -> 351686.97 | AF49: =AD48*$C$32*$C$33 -> 370477.65 | AG49: =AE48*$C$32*$C$33 -> 390272.31 | AH49: =AF48*$C$32*$C$33 -> 411124.6 | AI49: =AG48*$C$32*$C$33 -> 433091.04 | AJ49: =AH48*$C$32*$C$33 -> 456231.14 | AK49: =AI48*$C$32*$C$33 -> 480607.62 | AL49: =AJ48*$C$32*$C$33 -> 506286.54 | AM49: =AK48*$C$32*$C$33 -> 533337.49 | ... DC49: =DA48*$C$32*$C$33 -> 18373490
AF50: =AE49*$C$33 -> 333849.36 | AG50: =AE49*$C$32*$C$33 -> 351686.97 | AH50: =AF49*$C$32*$C$33 -> 370477.65 | AI50: =AG49*$C$32*$C$33 -> 390272.31 | AJ50: =AH49*$C$32*$C$33 -> 411124.6 | AK50: =AI49*$C$32*$C$33 -> 433091.04 | AL50: =AJ49*$C$32*$C$33 -> 456231.14 | AM50: =AK49*$C$32*$C$33 -> 480607.62 | AN50: =AL49*$C$32*$C$33 -> 506286.54 | ... DC50: =DA49*$C$32*$C$33 -> 16556945
AG51: =AF50*$C$33 -> 316916.48 | AH51: =AF50*$C$32*$C$33 -> 333849.36 | AI51: =AG50*$C$32*$C$33 -> 351686.97 | AJ51: =AH50*$C$32*$C$33 -> 370477.65 | AK51: =AI50*$C$32*$C$33 -> 390272.31 | AL51: =AJ50*$C$32*$C$33 -> 411124.6 | AM51: =AK50*$C$32*$C$33 -> 433091.04 | AN51: =AL50*$C$32*$C$33 -> 456231.14 | AO51: =AM50*$C$32*$C$33 -> 480607.62 | ... DC51: =DA50*$C$32*$C$33 -> 14919997
AH52: =AG51*$C$33 -> 300842.44 | AI52: =AG51*$C$32*$C$33 -> 316916.48 | AJ52: =AH51*$C$32*$C$33 -> 333849.36 | AK52: =AI51*$C$32*$C$33 -> 351686.97 | AL52: =AJ51*$C$32*$C$33 -> 370477.65 | AM52: =AK51*$C$32*$C$33 -> 390272.31 | AN52: =AL51*$C$32*$C$33 -> 411124.6 | AO52: =AM51*$C$32*$C$33 -> 433091.04 | AP52: =AN51*$C$32*$C$33 -> 456231.14 | ... DC52: =DA51*$C$32*$C$33 -> 13444891
AI53: =AH52*$C$33 -> 285583.67 | AJ53: =AH52*$C$32*$C$33 -> 300842.44 | AK53: =AI52*$C$32*$C$33 -> 316916.48 | AL53: =AJ52*$C$32*$C$33 -> 333849.36 | AM53: =AK52*$C$32*$C$33 -> 351686.97 | AN53: =AL52*$C$32*$C$33 -> 370477.65 | AO53: =AM52*$C$32*$C$33 -> 390272.31 | AP53: =AN52*$C$32*$C$33 -> 411124.6 | AQ53: =AO52*$C$32*$C$33 -> 433091.04 | ... DC53: =DA52*$C$32*$C$33 -> 12115625
AJ54: =AI53*$C$33 -> 271098.83 | AK54: =AI53*$C$32*$C$33 -> 285583.67 | AL54: =AJ53*$C$32*$C$33 -> 300842.44 | AM54: =AK53*$C$32*$C$33 -> 316916.48 | AN54: =AL53*$C$32*$C$33 -> 333849.36 | AO54: =AM53*$C$32*$C$33 -> 351686.97 | AP54: =AN53*$C$32*$C$33 -> 370477.65 | AQ54: =AO53*$C$32*$C$33 -> 390272.31 | AR54: =AP53*$C$32*$C$33 -> 411124.6 | ... DC54: =DA53*$C$32*$C$33 -> 10917781
AK55: =AJ54*$C$33 -> 257348.66 | AL55: =AJ54*$C$32*$C$33 -> 271098.83 | AM55: =AK54*$C$32*$C$33 -> 285583.67 | AN55: =AL54*$C$32*$C$33 -> 300842.44 | AO55: =AM54*$C$32*$C$33 -> 316916.48 | AP55: =AN54*$C$32*$C$33 -> 333849.36 | AQ55: =AO54*$C$32*$C$33 -> 351686.97 | AR55: =AP54*$C$32*$C$33 -> 370477.65 | AS55: =AQ54*$C$32*$C$33 -> 390272.31 | ... DC55: =DA54*$C$32*$C$33 -> 9838364.7
AL56: =AK55*$C$33 -> 244295.9 | AM56: =AK55*$C$32*$C$33 -> 257348.66 | AN56: =AL55*$C$32*$C$33 -> 271098.83 | AO56: =AM55*$C$32*$C$33 -> 285583.67 | AP56: =AN55*$C$32*$C$33 -> 300842.44 | AQ56: =AO55*$C$32*$C$33 -> 316916.48 | AR56: =AP55*$C$32*$C$33 -> 333849.36 | AS56: =AQ55*$C$32*$C$33 -> 351686.97 | AT56: =AR55*$C$32*$C$33 -> 370477.65 | ... DC56: =DA55*$C$32*$C$33 -> 8865667.9
AM57: =AL56*$C$33 -> 231905.18 | AN57: =AL56*$C$32*$C$33 -> 244295.9 | AO57: =AM56*$C$32*$C$33 -> 257348.66 | AP57: =AN56*$C$32*$C$33 -> 271098.83 | AQ57: =AO56*$C$32*$C$33 -> 285583.67 | AR57: =AP56*$C$32*$C$33 -> 300842.44 | AS57: =AQ56*$C$32*$C$33 -> 316916.48 | AT57: =AR56*$C$32*$C$33 -> 333849.36 | AU57: =AS56*$C$32*$C$33 -> 351686.97 | ... DC57: =DA56*$C$32*$C$33 -> 7989139.5
AN58: =AM57*$C$33 -> 220142.92 | AO58: =AM57*$C$32*$C$33 -> 231905.18 | AP58: =AN57*$C$32*$C$33 -> 244295.9 | AQ58: =AO57*$C$32*$C$33 -> 257348.66 | AR58: =AP57*$C$32*$C$33 -> 271098.83 | AS58: =AQ57*$C$32*$C$33 -> 285583.67 | AT58: =AR57*$C$32*$C$33 -> 300842.44 | AU58: =AS57*$C$32*$C$33 -> 316916.48 | AV58: =AT57*$C$32*$C$33 -> 333849.36 | ... DC58: =DA57*$C$32*$C$33 -> 7199271.4
AO59: =AN58*$C$33 -> 208977.24 | AP59: =AN58*$C$32*$C$33 -> 220142.92 | AQ59: =AO58*$C$32*$C$33 -> 231905.18 | AR59: =AP58*$C$32*$C$33 -> 244295.9 | AS59: =AQ58*$C$32*$C$33 -> 257348.66 | AT59: =AR58*$C$32*$C$33 -> 271098.83 | AU59: =AS58*$C$32*$C$33 -> 285583.67 | AV59: =AT58*$C$32*$C$33 -> 300842.44 | AW59: =AU58*$C$32*$C$33 -> 316916.48 | ... DC59: =DA58*$C$32*$C$33 -> 6487495.8
AP60: =AO59*$C$33 -> 198377.89 | AQ60: =AO59*$C$32*$C$33 -> 208977.24 | AR60: =AP59*$C$32*$C$33 -> 220142.92 | AS60: =AQ59*$C$32*$C$33 -> 231905.18 | AT60: =AR59*$C$32*$C$33 -> 244295.9 | AU60: =AS59*$C$32*$C$33 -> 257348.66 | AV60: =AT59*$C$32*$C$33 -> 271098.83 | AW60: =AU59*$C$32*$C$33 -> 285583.67 | AX60: =AV59*$C$32*$C$33 -> 300842.44 | ... DC60: =DA59*$C$32*$C$33 -> 5846091.8
AQ61: =AP60*$C$33 -> 188316.14 | AR61: =AP60*$C$32*$C$33 -> 198377.89 | AS61: =AQ60*$C$32*$C$33 -> 208977.24 | AT61: =AR60*$C$32*$C$33 -> 220142.92 | AU61: =AS60*$C$32*$C$33 -> 231905.18 | AV61: =AT60*$C$32*$C$33 -> 244295.9 | AW61: =AU60*$C$32*$C$33 -> 257348.66 | AX61: =AV60*$C$32*$C$33 -> 271098.83 | AY61: =AW60*$C$32*$C$33 -> 285583.67 | ... DC61: =DA60*$C$32*$C$33 -> 5268102
AR62: =AQ61*$C$33 -> 178764.72 | AS62: =AQ61*$C$32*$C$33 -> 188316.14 | AT62: =AR61*$C$32*$C$33 -> 198377.89 | AU62: =AS61*$C$32*$C$33 -> 208977.24 | AV62: =AT61*$C$32*$C$33 -> 220142.92 | AW62: =AU61*$C$32*$C$33 -> 231905.18 | AX62: =AV61*$C$32*$C$33 -> 244295.9 | AY62: =AW61*$C$32*$C$33 -> 257348.66 | AZ62: =AX61*$C$32*$C$33 -> 271098.83 | ... DC62: =DA61*$C$32*$C$33 -> 4747256.7
AS63: =AR62*$C$33 -> 169697.75 | AT63: =AR62*$C$32*$C$33 -> 178764.72 | AU63: =AS62*$C$32*$C$33 -> 188316.14 | AV63: =AT62*$C$32*$C$33 -> 198377.89 | AW63: =AU62*$C$32*$C$33 -> 208977.24 | AX63: =AV62*$C$32*$C$33 -> 220142.92 | AY63: =AW62*$C$32*$C$33 -> 231905.18 | AZ63: =AX62*$C$32*$C$33 -> 244295.9 | BA63: =AY62*$C$32*$C$33 -> 257348.66 | ... DC63: =DA62*$C$32*$C$33 -> 4277906.2
AT64: =AS63*$C$33 -> 161090.66 | AU64: =AS63*$C$32*$C$33 -> 169697.75 | AV64: =AT63*$C$32*$C$33 -> 178764.72 | AW64: =AU63*$C$32*$C$33 -> 188316.14 | AX64: =AV63*$C$32*$C$33 -> 198377.89 | AY64: =AW63*$C$32*$C$33 -> 208977.24 | AZ64: =AX63*$C$32*$C$33 -> 220142.92 | BA64: =AY63*$C$32*$C$33 -> 231905.18 | BB64: =AZ63*$C$32*$C$33 -> 244295.9 | ... DC64: =DA63*$C$32*$C$33 -> 3854959.3
AU65: =AT64*$C$33 -> 152920.12 | AV65: =AT64*$C$32*$C$33 -> 161090.66 | AW65: =AU64*$C$32*$C$33 -> 169697.75 | AX65: =AV64*$C$32*$C$33 -> 178764.72 | AY65: =AW64*$C$32*$C$33 -> 188316.14 | AZ65: =AX64*$C$32*$C$33 -> 198377.89 | BA65: =AY64*$C$32*$C$33 -> 208977.24 | BB65: =AZ64*$C$32*$C$33 -> 220142.92 | BC65: =BA64*$C$32*$C$33 -> 231905.18 | ... DC65: =DA64*$C$32*$C$33 -> 3473828.3
AV66: =AU65*$C$33 -> 145163.99 | AW66: =AU65*$C$32*$C$33 -> 152920.12 | AX66: =AV65*$C$32*$C$33 -> 161090.66 | AY66: =AW65*$C$32*$C$33 -> 169697.75 | AZ66: =AX65*$C$32*$C$33 -> 178764.72 | BA66: =AY65*$C$32*$C$33 -> 188316.14 | BB66: =AZ65*$C$32*$C$33 -> 198377.89 | BC66: =BA65*$C$32*$C$33 -> 208977.24 | BD66: =BB65*$C$32*$C$33 -> 220142.92 | ... DC66: =DA65*$C$32*$C$33 -> 3130378.7
AW67: =AV66*$C$33 -> 137801.25 | AX67: =AV66*$C$32*$C$33 -> 145163.99 | AY67: =AW66*$C$32*$C$33 -> 152920.12 | AZ67: =AX66*$C$32*$C$33 -> 161090.66 | BA67: =AY66*$C$32*$C$33 -> 169697.75 | BB67: =AZ66*$C$32*$C$33 -> 178764.72 | BC67: =BA66*$C$32*$C$33 -> 188316.14 | BD67: =BB66*$C$32*$C$33 -> 198377.89 | BE67: =BC66*$C$32*$C$33 -> 208977.24 | ... DC67: =DA66*$C$32*$C$33 -> 2820885.3
AX68: =AW67*$C$33 -> 130811.96 | AY68: =AW67*$C$32*$C$33 -> 137801.25 | AZ68: =AX67*$C$32*$C$33 -> 145163.99 | BA68: =AY67*$C$32*$C$33 -> 152920.12 | BB68: =AZ67*$C$32*$C$33 -> 161090.66 | BC68: =BA67*$C$32*$C$33 -> 169697.75 | BD68: =BB67*$C$32*$C$33 -> 178764.72 | BE68: =BC67*$C$32*$C$33 -> 188316.14 | BF68: =BD67*$C$32*$C$33 -> 198377.89 | ... DC68: =DA67*$C$32*$C$33 -> 2541990.8
AY69: =AX68*$C$33 -> 124177.16 | AZ69: =AX68*$C$32*$C$33 -> 130811.96 | BA69: =AY68*$C$32*$C$33 -> 137801.25 | BB69: =AZ68*$C$32*$C$33 -> 145163.99 | BC69: =BA68*$C$32*$C$33 -> 152920.12 | BD69: =BB68*$C$32*$C$33 -> 161090.66 | BE69: =BC68*$C$32*$C$33 -> 169697.75 | BF69: =BD68*$C$32*$C$33 -> 178764.72 | BG69: =BE68*$C$32*$C$33 -> 188316.14 | ... DC69: =DA68*$C$32*$C$33 -> 2290669.9
AZ70: =AY69*$C$33 -> 117878.87 | BA70: =AY69*$C$32*$C$33 -> 124177.16 | BB70: =AZ69*$C$32*$C$33 -> 130811.96 | BC70: =BA69*$C$32*$C$33 -> 137801.25 | BD70: =BB69*$C$32*$C$33 -> 145163.99 | BE70: =BC69*$C$32*$C$33 -> 152920.12 | BF70: =BD69*$C$32*$C$33 -> 161090.66 | BG70: =BE69*$C$32*$C$33 -> 169697.75 | BH70: =BF69*$C$32*$C$33 -> 178764.72 | ... DC70: =DA69*$C$32*$C$33 -> 2064196.6
BA71: =AZ70*$C$33 -> 111900.04 | BB71: =AZ70*$C$32*$C$33 -> 117878.87 | BC71: =BA70*$C$32*$C$33 -> 124177.16 | BD71: =BB70*$C$32*$C$33 -> 130811.96 | BE71: =BC70*$C$32*$C$33 -> 137801.25 | BF71: =BD70*$C$32*$C$33 -> 145163.99 | BG71: =BE70*$C$32*$C$33 -> 152920.12 | BH71: =BF70*$C$32*$C$33 -> 161090.66 | BI71: =BG70*$C$32*$C$33 -> 169697.75 | ... DC71: =DA70*$C$32*$C$33 -> 1860114.2
BB72: =BA71*$C$33 -> 106224.46 | BC72: =BA71*$C$32*$C$33 -> 111900.04 | BD72: =BB71*$C$32*$C$33 -> 117878.87 | BE72: =BC71*$C$32*$C$33 -> 124177.16 | BF72: =BD71*$C$32*$C$33 -> 130811.96 | BG72: =BE71*$C$32*$C$33 -> 137801.25 | BH72: =BF71*$C$32*$C$33 -> 145163.99 | BI72: =BG71*$C$32*$C$33 -> 152920.12 | BJ72: =BH71*$C$32*$C$33 -> 161090.66 | ... DC72: =DA71*$C$32*$C$33 -> 1676208.9
BC73: =BB72*$C$33 -> 100836.74 | BD73: =BB72*$C$32*$C$33 -> 106224.46 | BE73: =BC72*$C$32*$C$33 -> 111900.04 | BF73: =BD72*$C$32*$C$33 -> 117878.87 | BG73: =BE72*$C$32*$C$33 -> 124177.16 | BH73: =BF72*$C$32*$C$33 -> 130811.96 | BI73: =BG72*$C$32*$C$33 -> 137801.25 | BJ73: =BH72*$C$32*$C$33 -> 145163.99 | BK73: =BI72*$C$32*$C$33 -> 152920.12 | ... DC73: =DA72*$C$32*$C$33 -> 1510485.9
BD74: =BC73*$C$33 -> 95722.287 | BE74: =BC73*$C$32*$C$33 -> 100836.74 | BF74: =BD73*$C$32*$C$33 -> 106224.46 | BG74: =BE73*$C$32*$C$33 -> 111900.04 | BH74: =BF73*$C$32*$C$33 -> 117878.87 | BI74: =BG73*$C$32*$C$33 -> 124177.16 | BJ74: =BH73*$C$32*$C$33 -> 130811.96 | BK74: =BI73*$C$32*$C$33 -> 137801.25 | BL74: =BJ73*$C$32*$C$33 -> 145163.99 | ... DC74: =DA73*$C$32*$C$33 -> 1361147.6
BE75: =BD74*$C$33 -> 90867.24 | BF75: =BD74*$C$32*$C$33 -> 95722.287 | BG75: =BE74*$C$32*$C$33 -> 100836.74 | BH75: =BF74*$C$32*$C$33 -> 106224.46 | BI75: =BG74*$C$32*$C$33 -> 111900.04 | BJ75: =BH74*$C$32*$C$33 -> 117878.87 | BK75: =BI74*$C$32*$C$33 -> 124177.16 | BL75: =BJ74*$C$32*$C$33 -> 130811.96 | BM75: =BK74*$C$32*$C$33 -> 137801.25 | ... DC75: =DA74*$C$32*$C$33 -> 1226574
BF76: =BE75*$C$33 -> 86258.441 | BG76: =BE75*$C$32*$C$33 -> 90867.24 | BH76: =BF75*$C$32*$C$33 -> 95722.287 | BI76: =BG75*$C$32*$C$33 -> 100836.74 | BJ76: =BH75*$C$32*$C$33 -> 106224.46 | BK76: =BI75*$C$32*$C$33 -> 111900.04 | BL76: =BJ75*$C$32*$C$33 -> 117878.87 | BM76: =BK75*$C$32*$C$33 -> 124177.16 | BN76: =BL75*$C$32*$C$33 -> 130811.96 | ... DC76: =DA75*$C$32*$C$33 -> 1105305.5
BG77: =BF76*$C$33 -> 81883.402 | BH77: =BF76*$C$32*$C$33 -> 86258.441 | BI77: =BG76*$C$32*$C$33 -> 90867.24 | BJ77: =BH76*$C$32*$C$33 -> 95722.287 | BK77: =BI76*$C$32*$C$33 -> 100836.74 | BL77: =BJ76*$C$32*$C$33 -> 106224.46 | BM77: =BK76*$C$32*$C$33 -> 111900.04 | BN77: =BL76*$C$32*$C$33 -> 117878.87 | BO77: =BM76*$C$32*$C$33 -> 124177.16 | ... DC77: =DA76*$C$32*$C$33 -> 996026.41
BH78: =BG77*$C$33 -> 77730.265 | BI78: =BG77*$C$32*$C$33 -> 81883.402 | BJ78: =BH77*$C$32*$C$33 -> 86258.441 | BK78: =BI77*$C$32*$C$33 -> 90867.24 | BL78: =BJ77*$C$32*$C$33 -> 95722.287 | BM78: =BK77*$C$32*$C$33 -> 100836.74 | BN78: =BL77*$C$32*$C$33 -> 106224.46 | BO78: =BM77*$C$32*$C$33 -> 111900.04 | BP78: =BN77*$C$32*$C$33 -> 117878.87 | ... DC78: =DA77*$C$32*$C$33 -> 897551.54
BI79: =BH78*$C$33 -> 73787.776 | BJ79: =BH78*$C$32*$C$33 -> 77730.265 | BK79: =BI78*$C$32*$C$33 -> 81883.402 | BL79: =BJ78*$C$32*$C$33 -> 86258.441 | BM79: =BK78*$C$32*$C$33 -> 90867.24 | BN79: =BL78*$C$32*$C$33 -> 95722.287 | BO79: =BM78*$C$32*$C$33 -> 100836.74 | BP79: =BN78*$C$32*$C$33 -> 106224.46 | BQ79: =BO78*$C$32*$C$33 -> 111900.04 | ... DC79: =DA78*$C$32*$C$33 -> 808812.66
BJ80: =BI79*$C$33 -> 70045.25 | BK80: =BI79*$C$32*$C$33 -> 73787.776 | BL80: =BJ79*$C$32*$C$33 -> 77730.265 | BM80: =BK79*$C$32*$C$33 -> 81883.402 | BN80: =BL79*$C$32*$C$33 -> 86258.441 | BO80: =BM79*$C$32*$C$33 -> 90867.24 | BP80: =BN79*$C$32*$C$33 -> 95722.287 | BQ80: =BO79*$C$32*$C$33 -> 100836.74 | BR80: =BP79*$C$32*$C$33 -> 106224.46 | ... DC80: =DA79*$C$32*$C$33 -> 728847.19
BK81: =BJ80*$C$33 -> 66492.546 | BL81: =BJ80*$C$32*$C$33 -> 70045.25 | BM81: =BK80*$C$32*$C$33 -> 73787.776 | BN81: =BL80*$C$32*$C$33 -> 77730.265 | BO81: =BM80*$C$32*$C$33 -> 81883.402 | BP81: =BN80*$C$32*$C$33 -> 86258.441 | BQ81: =BO80*$C$32*$C$33 -> 90867.24 | BR81: =BP80*$C$32*$C$33 -> 95722.287 | BS81: =BQ80*$C$32*$C$33 -> 100836.74 | ... DC81: =DA80*$C$32*$C$33 -> 656787.72
BL82: =BK81*$C$33 -> 63120.036 | BM82: =BK81*$C$32*$C$33 -> 66492.546 | BN82: =BL81*$C$32*$C$33 -> 70045.25 | BO82: =BM81*$C$32*$C$33 -> 73787.776 | BP82: =BN81*$C$32*$C$33 -> 77730.265 | BQ82: =BO81*$C$32*$C$33 -> 81883.402 | BR82: =BP81*$C$32*$C$33 -> 86258.441 | BS82: =BQ81*$C$32*$C$33 -> 90867.24 | BT82: =BR81*$C$32*$C$33 -> 95722.287 | ... DC82: =DA81*$C$32*$C$33 -> 591852.61
BM83: =BL82*$C$33 -> 59918.579 | BN83: =BL82*$C$32*$C$33 -> 63120.036 | BO83: =BM82*$C$32*$C$33 -> 66492.546 | BP83: =BN82*$C$32*$C$33 -> 70045.25 | BQ83: =BO82*$C$32*$C$33 -> 73787.776 | BR83: =BP82*$C$32*$C$33 -> 77730.265 | BS83: =BQ82*$C$32*$C$33 -> 81883.402 | BT83: =BR82*$C$32*$C$33 -> 86258.441 | BU83: =BS82*$C$32*$C$33 -> 90867.24 | ... DC83: =DA82*$C$32*$C$33 -> 533337.49
BN84: =BM83*$C$33 -> 56879.501 | BO84: =BM83*$C$32*$C$33 -> 59918.579 | BP84: =BN83*$C$32*$C$33 -> 63120.036 | BQ84: =BO83*$C$32*$C$33 -> 66492.546 | BR84: =BP83*$C$32*$C$33 -> 70045.25 | BS84: =BQ83*$C$32*$C$33 -> 73787.776 | BT84: =BR83*$C$32*$C$33 -> 77730.265 | BU84: =BS83*$C$32*$C$33 -> 81883.402 | BV84: =BT83*$C$32*$C$33 -> 86258.441 | ... DC84: =DA83*$C$32*$C$33 -> 480607.62
BO85: =BN84*$C$33 -> 53994.565 | BP85: =BN84*$C$32*$C$33 -> 56879.501 | BQ85: =BO84*$C$32*$C$33 -> 59918.579 | BR85: =BP84*$C$32*$C$33 -> 63120.036 | BS85: =BQ84*$C$32*$C$33 -> 66492.546 | BT85: =BR84*$C$32*$C$33 -> 70045.25 | BU85: =BS84*$C$32*$C$33 -> 73787.776 | BV85: =BT84*$C$32*$C$33 -> 77730.265 | BW85: =BU84*$C$32*$C$33 -> 81883.402 | ... DC85: =DA84*$C$32*$C$33 -> 433091.04
BP86: =BO85*$C$33 -> 51255.954 | BQ86: =BO85*$C$32*$C$33 -> 53994.565 | BR86: =BP85*$C$32*$C$33 -> 56879.501 | BS86: =BQ85*$C$32*$C$33 -> 59918.579 | BT86: =BR85*$C$32*$C$33 -> 63120.036 | BU86: =BS85*$C$32*$C$33 -> 66492.546 | BV86: =BT85*$C$32*$C$33 -> 70045.25 | BW86: =BU85*$C$32*$C$33 -> 73787.776 | BX86: =BV85*$C$32*$C$33 -> 77730.265 | ... DC86: =DA85*$C$32*$C$33 -> 390272.31
BQ87: =BP86*$C$33 -> 48656.245 | BR87: =BP86*$C$32*$C$33 -> 51255.954 | BS87: =BQ86*$C$32*$C$33 -> 53994.565 | BT87: =BR86*$C$32*$C$33 -> 56879.501 | BU87: =BS86*$C$32*$C$33 -> 59918.579 | BV87: =BT86*$C$32*$C$33 -> 63120.036 | BW87: =BU86*$C$32*$C$33 -> 66492.546 | BX87: =BV86*$C$32*$C$33 -> 70045.25 | BY87: =BW86*$C$32*$C$33 -> 73787.776 | ... DC87: =DA86*$C$32*$C$33 -> 351686.97
BR88: =BQ87*$C$33 -> 46188.394 | BS88: =BQ87*$C$32*$C$33 -> 48656.245 | BT88: =BR87*$C$32*$C$33 -> 51255.954 | BU88: =BS87*$C$32*$C$33 -> 53994.565 | BV88: =BT87*$C$32*$C$33 -> 56879.501 | BW88: =BU87*$C$32*$C$33 -> 59918.579 | BX88: =BV87*$C$32*$C$33 -> 63120.036 | BY88: =BW87*$C$32*$C$33 -> 66492.546 | BZ88: =BX87*$C$32*$C$33 -> 70045.25 | ... DC88: =DA87*$C$32*$C$33 -> 316916.48
BS89: =BR88*$C$33 -> 43845.713 | BT89: =BR88*$C$32*$C$33 -> 46188.394 | BU89: =BS88*$C$32*$C$33 -> 48656.245 | BV89: =BT88*$C$32*$C$33 -> 51255.954 | BW89: =BU88*$C$32*$C$33 -> 53994.565 | BX89: =BV88*$C$32*$C$33 -> 56879.501 | BY89: =BW88*$C$32*$C$33 -> 59918.579 | BZ89: =BX88*$C$32*$C$33 -> 63120.036 | CA89: =BY88*$C$32*$C$33 -> 66492.546 | ... DC89: =DA88*$C$32*$C$33 -> 285583.67
BT90: =BS89*$C$33 -> 41621.852 | BU90: =BS89*$C$32*$C$33 -> 43845.713 | BV90: =BT89*$C$32*$C$33 -> 46188.394 | BW90: =BU89*$C$32*$C$33 -> 48656.245 | BX90: =BV89*$C$32*$C$33 -> 51255.954 | BY90: =BW89*$C$32*$C$33 -> 53994.565 | BZ90: =BX89*$C$32*$C$33 -> 56879.501 | CA90: =BY89*$C$32*$C$33 -> 59918.579 | CB90: =BZ89*$C$32*$C$33 -> 63120.036 | ... DC90: =DA89*$C$32*$C$33 -> 257348.66
BU91: =BT90*$C$33 -> 39510.787 | BV91: =BT90*$C$32*$C$33 -> 41621.852 | BW91: =BU90*$C$32*$C$33 -> 43845.713 | BX91: =BV90*$C$32*$C$33 -> 46188.394 | BY91: =BW90*$C$32*$C$33 -> 48656.245 | BZ91: =BX90*$C$32*$C$33 -> 51255.954 | CA91: =BY90*$C$32*$C$33 -> 53994.565 | CB91: =BZ90*$C$32*$C$33 -> 56879.501 | CC91: =CA90*$C$32*$C$33 -> 59918.579 | ... DC91: =DA90*$C$32*$C$33 -> 231905.18
BV92: =BU91*$C$33 -> 37506.794 | BW92: =BU91*$C$32*$C$33 -> 39510.787 | BX92: =BV91*$C$32*$C$33 -> 41621.852 | BY92: =BW91*$C$32*$C$33 -> 43845.713 | BZ92: =BX91*$C$32*$C$33 -> 46188.394 | CA92: =BY91*$C$32*$C$33 -> 48656.245 | CB92: =BZ91*$C$32*$C$33 -> 51255.954 | CC92: =CA91*$C$32*$C$33 -> 53994.565 | CD92: =CB91*$C$32*$C$33 -> 56879.501 | ... DC92: =DA91*$C$32*$C$33 -> 208977.24
BW93: =BV92*$C$33 -> 35604.445 | BX93: =BV92*$C$32*$C$33 -> 37506.794 | BY93: =BW92*$C$32*$C$33 -> 39510.787 | BZ93: =BX92*$C$32*$C$33 -> 41621.852 | CA93: =BY92*$C$32*$C$33 -> 43845.713 | CB93: =BZ92*$C$32*$C$33 -> 46188.394 | CC93: =CA92*$C$32*$C$33 -> 48656.245 | CD93: =CB92*$C$32*$C$33 -> 51255.954 | CE93: =CC92*$C$32*$C$33 -> 53994.565 | ... DC93: =DA92*$C$32*$C$33 -> 188316.14
BX94: =BW93*$C$33 -> 33798.583 | BY94: =BW93*$C$32*$C$33 -> 35604.445 | BZ94: =BX93*$C$32*$C$33 -> 37506.794 | CA94: =BY93*$C$32*$C$33 -> 39510.787 | CB94: =BZ93*$C$32*$C$33 -> 41621.852 | CC94: =CA93*$C$32*$C$33 -> 43845.713 | CD94: =CB93*$C$32*$C$33 -> 46188.394 | CE94: =CC93*$C$32*$C$33 -> 48656.245 | CF94: =CD93*$C$32*$C$33 -> 51255.954 | ... DC94: =DA93*$C$32*$C$33 -> 169697.75
BY95: =BX94*$C$33 -> 32084.314 | BZ95: =BX94*$C$32*$C$33 -> 33798.583 | CA95: =BY94*$C$32*$C$33 -> 35604.445 | CB95: =BZ94*$C$32*$C$33 -> 37506.794 | CC95: =CA94*$C$32*$C$33 -> 39510.787 | CD95: =CB94*$C$32*$C$33 -> 41621.852 | CE95: =CC94*$C$32*$C$33 -> 43845.713 | CF95: =CD94*$C$32*$C$33 -> 46188.394 | CG95: =CE94*$C$32*$C$33 -> 48656.245 | ... DC95: =DA94*$C$32*$C$33 -> 152920.12
BZ96: =BY95*$C$33 -> 30456.994 | CA96: =BY95*$C$32*$C$33 -> 32084.314 | CB96: =BZ95*$C$32*$C$33 -> 33798.583 | CC96: =CA95*$C$32*$C$33 -> 35604.445 | CD96: =CB95*$C$32*$C$33 -> 37506.794 | CE96: =CC95*$C$32*$C$33 -> 39510.787 | CF96: =CD95*$C$32*$C$33 -> 41621.852 | CG96: =CE95*$C$32*$C$33 -> 43845.713 | CH96: =CF95*$C$32*$C$33 -> 46188.394 | ... DC96: =DA95*$C$32*$C$33 -> 137801.25
CA97: =BZ96*$C$33 -> 28912.211 | CB97: =BZ96*$C$32*$C$33 -> 30456.994 | CC97: =CA96*$C$32*$C$33 -> 32084.314 | CD97: =CB96*$C$32*$C$33 -> 33798.583 | CE97: =CC96*$C$32*$C$33 -> 35604.445 | CF97: =CD96*$C$32*$C$33 -> 37506.794 | CG97: =CE96*$C$32*$C$33 -> 39510.787 | CH97: =CF96*$C$32*$C$33 -> 41621.852 | CI97: =CG96*$C$32*$C$33 -> 43845.713 | ... DC97: =DA96*$C$32*$C$33 -> 124177.16
CB98: =CA97*$C$33 -> 27445.78 | CC98: =CA97*$C$32*$C$33 -> 28912.211 | CD98: =CB97*$C$32*$C$33 -> 30456.994 | CE98: =CC97*$C$32*$C$33 -> 32084.314 | CF98: =CD97*$C$32*$C$33 -> 33798.583 | CG98: =CE97*$C$32*$C$33 -> 35604.445 | CH98: =CF97*$C$32*$C$33 -> 37506.794 | CI98: =CG97*$C$32*$C$33 -> 39510.787 | CJ98: =CH97*$C$32*$C$33 -> 41621.852 | ... DC98: =DA97*$C$32*$C$33 -> 111900.04
CC99: =CB98*$C$33 -> 26053.726 | CD99: =CB98*$C$32*$C$33 -> 27445.78 | CE99: =CC98*$C$32*$C$33 -> 28912.211 | CF99: =CD98*$C$32*$C$33 -> 30456.994 | CG99: =CE98*$C$32*$C$33 -> 32084.314 | CH99: =CF98*$C$32*$C$33 -> 33798.583 | CI99: =CG98*$C$32*$C$33 -> 35604.445 | CJ99: =CH98*$C$32*$C$33 -> 37506.794 | CK99: =CI98*$C$32*$C$33 -> 39510.787 | ... DC99: =DA98*$C$32*$C$33 -> 100836.74
CD100: =CC99*$C$33 -> 24732.278 | CE100: =CC99*$C$32*$C$33 -> 26053.726 | CF100: =CD99*$C$32*$C$33 -> 27445.78 | CG100: =CE99*$C$32*$C$33 -> 28912.211 | CH100: =CF99*$C$32*$C$33 -> 30456.994 | CI100: =CG99*$C$32*$C$33 -> 32084.314 | CJ100: =CH99*$C$32*$C$33 -> 33798.583 | CK100: =CI99*$C$32*$C$33 -> 35604.445 | CL100: =CJ99*$C$32*$C$33 -> 37506.794 | ... DC100: =DA99*$C$32*$C$33 -> 90867.24
CE101: =CD100*$C$33 -> 23477.854 | CF101: =CD100*$C$32*$C$33 -> 24732.278 | CG101: =CE100*$C$32*$C$33 -> 26053.726 | CH101: =CF100*$C$32*$C$33 -> 27445.78 | CI101: =CG100*$C$32*$C$33 -> 28912.211 | CJ101: =CH100*$C$32*$C$33 -> 30456.994 | CK101: =CI100*$C$32*$C$33 -> 32084.314 | CL101: =CJ100*$C$32*$C$33 -> 33798.583 | CM101: =CK100*$C$32*$C$33 -> 35604.445 | ... DC101: =DA100*$C$32*$C$33 -> 81883.402
...

Sheet Straight Debt_Extend
B2: Straight Debt
B3: Valuation Date | C3: =Input!C2 -> 45838
B5: Risky Rate:
B6: ='Risky Rate'!B3 -> Rfr | C6: ='Risky Rate'!D3 -> 0.03719811
B7: ='Risky Rate'!B4 -> OAS | C7: ='Risky Rate'!D4 -> 0.14850175
B8: ='Risky Rate'!B5 -> Liquidity | C8: ='Risky Rate'!D5 -> 0.015
B9: ='Risky Rate'!B6 -> Other Risk | C9: ='Risky Rate'!D6 -> 0.28763281
B10: Total | C10: =SUM(C6:C9) -> 0.48833267
B13: Date | C13: Interest Payment | D13: Principal Repayment | E13: TTM | F13: PV
B14: =Input!B22 -> 45291
B15: =Input!B23 -> 45657
B16: =Input!B24 -> 46022 | C16: =Input!C24 -> 1000000 | E16: =YEARFRAC(B16,$C$3,3) -> 0.50410959 | F16: =SUM(C16:D16)/(1+$C$10)^E16 -> 818352.22
B17: =Input!B25 -> 46387 | C17: =Input!C25 -> 1000000 | E17: =YEARFRAC(B17,$C$3,3) -> 1.5041096 | F17: =SUM(C17:D17)/(1+$C$10)^E17 -> 549844.97
B18: =Input!B26 -> 46582 | C18: =Input!C26 -> 534246.58 | D18: =Input!C4 -> 10000000 | E18: =YEARFRAC(B18,$C$3,3) -> 2.0383562 | F18: =SUM(C18:D18)/(1+$C$10)^E18 -> 4683595.1
B19: Total PV | F19: =ROUND(SUM(F14:F18),-4) -> 6050000

Sheet Risky Rate
C2: 1.04-Y | D2: 2.04-Y
B3: Rfr | C3: =J28 -> 0.039623726 | D3: =J29 -> 0.03719811
B4: OAS | C4: =J18%% -> 0.14850175 | D4: =C4 -> 0.14850175
B5: Liquidity | C5: 0.015 | D5: =C5 -> 0.015
B6: Other Risk | C6: 0.28763281 | D6: =C6 -> 0.28763281 | E6: Backsolved and calibrated by day-1 valuation to match the issue price
B7: Risky Rate | C7: =SUM(C3:C6) -> 0.49075828 | D7: =SUM(D3:D6) -> 0.48833267
B10: Ticker | C10: Issuer | F10: S&P Rating | G10: Moody's Rating | H10: Fitch Rating | I10: OAS (bps) | J10: Firm OAS (bps)
B11: BP2798786 Corp | C11: ACProducts Holdings Inc | F11: CCC- | G11: Ca | H11: N/A | I11: 2806.55 | J11: =I11 -> 2806.55
B12: ZO4200051 Corp | C12: Cornerstone Building Brands Inc | F12: CCC | G12: Caa2 | H12: N/A | I12: 1270.8 | J12: =AVERAGE(I12:I13) -> 928.45
B13: BM6056535 Corp | C13: CP Atlas Buyer Inc | F13: CCC- | G13: Caa2 | H13: N/A | I13: 586.1 | J13: =I13 -> 586.1
B14: ZB8403683 Corp | C14: Vestel Elektronik Sanayi ve Ticaret AS | F14: N/A | G14: Caa1 | H14: B- | I14: 1334.99 | J14: =I14 -> 1334.99
B15: BO2210397 Corp | C15: Victoria PLC | F15: CCC+ | G15: Caa1 | H15: B- | I15: 595.61 | J15: =AVERAGE(I15:I16) -> 2361.885
B16: BO4852279 Corp | C16: Victoria PLC | F16: CCC+ | G16: Caa1 | H16: B- | I16: 4128.16
B17: YW5767903 Corp | C17: Wilsonart LLC | F17: B- | G17: Caa2 | H17: N/A | I17: 892.13 | J17: =I17 -> 892.13
J18: =AVERAGE(J11:J17) -> 1485.0175
I24: Tenor | J24: Rfr
I25: 1 | J25: 0.03972
I26: 2 | J26: 0.03721
I27: 3 | J27: 0.0369
I28: ='Full CB'!C17 -> 1.0383562 | J28: =TREND(J25:J26,I25:I26,I28) -> 0.039623726
I29: ='Full CB_Extend'!C17 -> 2.0383562 | J29: =TREND(J26:J27,I26:I27,I29) -> 0.03719811

Sheet Vol
B2: Ticker | C2: Name | G2: 270-Day Vol | I2: ='Full CB'!C17*260 -> 269.9726
B3: 021240 KS Equity | C3: Coway Co Ltd | G3: 41.9
B4: 192400 KS Equity | C4: Cuckoo Holdings Co Ltd | G4: 30.008
B5: SCNP IJ Equity | C5: Selaras Citra Nusantara Perkasa PT | G5: 69.575
B6: CROMPTON IN Equity | C6: Crompton Greaves Consumer Electricals Ltd | H6: no air purifier in the product line (see website) as at 30 June 2025
B7: 000651 CH Equity | C7: Gree Electric Appliances Inc of Zhuhai | G7: 26.858
B8: 002032 CH Equity | C8: Zhejiang Supor Co Ltd | G8: 25.659
B9: 605117 CH Equity | C9: Ningbo Deye Technology Co Ltd | G9: 50.265
B10: 5909 JP Equity | C10: Corona Corp | G10: 21.418
B11: 5951 JP Equity | C11: Dainichi Co Ltd | G11: 21.501
B12: 300247 CH Equity | C12: Youngy Health Co Ltd | G12: 53.317
B13: 4609 TT Equity | C13: Airlux Electrical Co Ltd | H13: no air purifier in the product line (see website) as at 30 June 2025
B14: Average | G14: =AVERAGE(G3:G13)% -> 0.37833444
B16: Ticker | C16: Name | G16: 530-Day Vol | I16: ='Full CB_Extend'!C17*260 -> 529.9726
B17: 021240 KS Equity | C17: Coway Co Ltd | G17: 36.627
B18: 192400 KS Equity | C18: Cuckoo Holdings Co Ltd | G18: 30.953
B19: SCNP IJ Equity | C19: Selaras Citra Nusantara Perkasa PT | G19: 69.261
B20: 000651 CH Equity | C20: Gree Electric Appliances Inc of Zhuhai | G20: 25.856
B21: 002032 CH Equity | C21: Zhejiang Supor Co Ltd | G21: 26.673
B22: 605117 CH Equity | C22: Ningbo Deye Technology Co Ltd | G22: 53.41
B23: 5909 JP Equity | C23: Corona Corp | G23: 18.387
B24: 5951 JP Equity | C24: Dainichi Co Ltd | G24: 20.189
B25: 300247 CH Equity | C25: Youngy Health Co Ltd | G25: 46.767
B26: Average | G26: =AVERAGE(G17:G25)% -> 0.36458111

Sheet Credit Profile
A1: Ticker | B1: N/A
A2: Company Name | B2: Delos Living LLC
A3: Latest Fiscal Period | B3: =DATE(2024,12,31) -> 45657
A4: Currency | B4: USD
A5: Moody's Financial Metrics™ | B5: 2023 | C5: 2018
C6: 2020
A7: Ratio Analysis | M7: Advanced Scoring | P7: Simple Scoring
A8: No. | B8: Ratio | C8: Value | D8: Rating | E8: Score | M8: Rating | N8: Score | P8: Rating | Q8: Ref | R8: Score
A9: 1 | B9: Debt / EBITDA | C9: =C38/C29 -> -4.0066078 | D9: C | E9: =IFERROR(INDEX($R$9:$R$16,MATCH($D9,$P$9:$P$16,0)),"") -> 21 | M9: Aaa | N9: =N10-1 -> 1 | P9: Aaa | Q9: Aaa | R9: 1
A10: =A9+1 -> 2 | B10: EBITA / Interest Expense | C10: =C29/C33 -> -1.6899959 | D10: C | E10: =IFERROR(INDEX($R$9:$R$16,MATCH($D10,$P$9:$P$16,0)),"") -> 21 | M10: Aa1 | N10: =N11-1 -> 2 | P10: Aa | Q10: Aa2 | R10: 3
A11: =A10+1 -> 3 | B11: Revenue (in US$ billion) | C11: =C26 -> 0.035008 | D11: C | E11: =IFERROR(INDEX($R$9:$R$16,MATCH($D11,$P$9:$P$16,0)),"") -> 21 | M11: Aa2 | N11: =N12-1 -> 3 | P11: A | Q11: A2 | R11: 6
A12: =A11+1 -> 4 | B12: RCF / Net Debt | C12: =IF(C39<=0,"N/A",C48/C39) -> -0.42216435 | D12: #N/A | F12: Not available for Financial Metrics™ in 2023 | M12: Aa3 | N12: =N13-1 -> 4 | P12: Baa | Q12: Baa2 | R12: 9
A13: =A12+1 -> 5 | B13: EBITA Margin | C13: =C31/C27 -> -0.96946412 | D13: C | E13: =IFERROR(INDEX($R$9:$R$16,MATCH($D13,$P$9:$P$16,0)),"") -> 21 | M13: A1 | N13: =N14-1 -> 5 | P13: Ba | Q13: Ba2 | R13: 12
A14: =A13+1 -> 6 | B14: Operating Margin | C14: =C32/C27 -> -1.0335923 | D14: C | E14: =IFERROR(INDEX($R$9:$R$16,MATCH($D14,$P$9:$P$16,0)),"") -> 21 | M14: A2 | N14: =N15-1 -> 6 | P14: B | Q14: B2 | R14: 15
A15: =A14+1 -> 7 | B15: FFO / Debt | C15: =IF(C38<=0,"N/A",C44/C38) -> -0.39797229 | D15: C | E15: =IFERROR(INDEX($R$9:$R$16,MATCH($D15,$P$9:$P$16,0)),"") -> 21 | M15: A3 | N15: =N16-1 -> 7 | P15: Caa | Q15: Caa2 | R15: 18
A16: =A15+1 -> 8 | B16: (FFO + Int Exp) / Int Exp | C16: =IF(C33<=0,"N/A",(C44+C33)/C33) -> -1.6947303 | D16: C | E16: =IFERROR(INDEX($R$9:$R$16,MATCH($D16,$P$9:$P$16,0)),"") -> 21 | M16: Baa1 | N16: =N17-1 -> 8 | P16: C | Q16: C | R16: 21
A17: =A16+1 -> 9 | B17: EBITA / Average Assets | C17: =C31/AVERAGE(C35:D35) -> -0.639291 | D17: C | E17: =IFERROR(INDEX($R$9:$R$16,MATCH($D17,$P$9:$P$16,0)),"") -> 21 | M17: Baa2 | N17: =N18-1 -> 9
A18: =A17+1 -> 10 | B18: CAPEX / Depreciation Expense | C18: =C49/C30 -> 0.14467698 | D18: C | E18: =IFERROR(INDEX($R$9:$R$16,MATCH($D18,$P$9:$P$16,0)),"") -> 21 | M18: Baa3 | N18: =N19-1 -> 10
A19: =A18+1 -> 11 | B19: Revenue Volatility | C19: =_xlfn.STDEV.S(C28:G28) -> #DIV/0! | D19: #DIV/0! | E19: =IFERROR(INDEX($R$9:$R$16,MATCH($D19,$P$9:$P$16,0)),"") | M19: Ba1 | N19: =N20-1 -> 11
B20: Average | E20: =AVERAGE(E9:E19) -> 21 | M20: Ba2 | N20: =N21-1 -> 12
B21: Rating | E21: =INDEX($M$9:$M$29,MATCH(E20,$N$9:$N$29,1)) -> C | M21: Ba3 | N21: =N22-1 -> 13
M22: B1 | N22: =N23-1 -> 14
A23: Financial Data (in local currency million, unless specified; all figures are show positive to their nature) | M23: B2 | N23: =N24-1 -> 15
A24: Fin Stmt | B24: Year | C24: T | D24: T-1 | E24: T-2 | F24: T-3 | G24: T-4 | H24: T-5 | M24: B3 | N24: =N25-1 -> 16
C25: =YEAR(B3) -> 2024 | D25: =C25-1 -> 2023 | E25: =D25-1 -> 2022 | F25: =E25-1 -> 2021 | G25: =F25-1 -> 2020 | H25: =G25-1 -> 2019 | M25: Caa1 | N25: =N26-1 -> 17
A26: PL | B26: Revenue (in US$ billion) | C26: =C27/1000000000 -> 0.035008 | M26: Caa2 | N26: =N27-1 -> 18
A27: PL | B27: Revenue | C27: ='2024FS'!D2 -> 35008000 | M27: Caa3 | N27: =N28-1 -> 19
A28: Cal | B28: Revenue Growth | C28: =IFERROR(C27/D27-1,"") | D28: =IFERROR(D27/E27-1,"") | E28: =IFERROR(E27/F27-1,"") | F28: =IFERROR(F27/G27-1,"") | G28: =IFERROR(G27/H27-1,"") | M28: Ca | N28: =N29-1 -> 20
A29: PL | B29: EBITDA | C29: ='2024FS'!D12 -> -32840000 | M29: C | N29: 21
A30: PL | B30: Depreciation | C30: ='2024FS'!D11 -> 1099000 | I30: Expense: positive
A31: PL | B31: EBITA | C31: ='2024FS'!D10 -> -33939000
A32: PL | B32: Operating Income (EBIT) | C32: ='2024FS'!D8 -> -36184000
A33: PL | B33: Interest Expense | C33: ='2024FS'!D7 -> 19432000 | I33: Expense: positive
A34: BS | B34: Cash and Cash Equivalent | C34: =SUM('2024FS'!D18:D19) -> 7540000
A35: BS | B35: Assets | C35: ='2024FS'!D21 -> 38364000 | D35: ='2024FS'!D22 -> 67813000
A36: BS | B36: Short-Term Debt | C36: =-SUM('2024FS'!D24:D25) -> 13258000
A37: BS | B37: Long-Term Debt | C37: =-SUM('2024FS'!D26:D27) -> 118319000
A38: Cal | B38: Debt | C38: =C36+C37 -> 131577000
A39: Cal | B39: Net Debt | C39: =C36+C37-C34 -> 124037000
A40: BS | B40: Deferred Taxes | C40: 0
A41: BS | B41: Minority Interest
A42: BS | B42: Book Equity | C42: ='2024FS'!D29 -> -583702000
A43: Cal | B43: Book Capitalization | C43: =C36+C37+C40+C41+C42 -> -452125000
A44: CF | B44: Funds from Operation (FFO) | C44: =C29-C33-'2024FS'!D5 -> -52364000
A45: CF | B45: Preferred Dividends
A46: CF | B46: Common Dividends
A47: CF | B47: Minority Dividends | C47: 0
A48: Cal | B48: Retained Cashflow (RCF) | C48: =C44-C45-C46-C47 -> -52364000
A49: CF | B49: CAPEX | C49: ='2024FS'!D31 -> 159000 | I49: Expense: positive

Sheet Info from Client->

Sheet 2024FS
C1: in USD'000 | D1: in USD
A2: Revenue | C2: 35008 | D2: =C2*1000 -> 35008000
A4: Net Profit | C4: -55708 | D4: =C4*1000 -> -55708000
A5: Add: Tax | C5: 92 | D5: =C5*1000 -> 92000
A6: EBT | C6: =SUM(C4:C5) -> -55616 | D6: =C6*1000 -> -55616000
A7: Add: Interest | C7: 19432 | D7: =C7*1000 -> 19432000
A8: EBIT | C8: =SUM(C6:C7) -> -36184 | D8: =C8*1000 -> -36184000
A9: Add: Amortisation | C9: 2245 | D9: =C9*1000 -> 2245000 | E9: Amortization of operating lease right of use assets
A10: EBITA | C10: =SUM(C8:C9) -> -33939 | D10: =C10*1000 -> -33939000
A11: Add: Depreciation | C11: 1099 | D11: =C11*1000 -> 1099000
A12: EBITDA | C12: =SUM(C10:C11) -> -32840 | D12: =C12*1000 -> -32840000
A18: Cash and cash equivalents | C18: 5715 | D18: =C18*1000 -> 5715000
A19: Restricted cash | C19: 1825 | D19: =C19*1000 -> 1825000
A21: Total Asset in 2024 | C21: 38364 | D21: =C21*1000 -> 38364000
A22: Total Asset in 2023 | C22: 67813 | D22: =C22*1000 -> 67813000
A24: Debt, current portion | C24: -11425 | D24: =C24*1000 -> -11425000
A25: Operating lease liabilities, current portion | C25: -1833 | D25: =C25*1000 -> -1833000
A26: Long term debt, net of current portion | C26: -106312 | D26: =C26*1000 -> -106312000
A27: Operating lease liabilities, net of current portion | C27: -12007 | D27: =C27*1000 -> -12007000
A29: Total NAV | C29: -583702 | D29: =C29*1000 -> -583702000
A31: Capex | C31: 159 | D31: =C31*1000 -> 159000
